{"estado":"Colima","segmentos":{"195394792":{"id":195394792,"lat":18.750804,"lon":-103.719957,"rt":2,"ciudad":"","sug":"Progreso","conf":100,"vec":"Pino Suárez","celda":"37345","visto":"2026-07-23"},"276680580":{"id":276680580,"lat":18.824062,"lon":-103.700829,"rt":1,"ciudad":"San Miguel del Ojo de Agua","sug":"Ahabram Torres","conf":100,"vec":"","celda":"38405","visto":"2026-07-23"},"276680579":{"id":276680579,"lat":18.824321,"lon":-103.702036,"rt":1,"ciudad":"San Miguel del Ojo de Agua","sug":"Ahabram Torres","conf":100,"vec":"","celda":"38405","visto":"2026-07-23"},"258199107":{"id":258199107,"lat":18.918111,"lon":-104.070595,"rt":2,"ciudad":"Cuyutlán","sug":"Miguel Hidalgo","conf":100,"vec":"Av. Lopez Mateos","celda":"38929","visto":"2026-07-24"},"258199101":{"id":258199101,"lat":18.919168,"lon":-104.069714,"rt":2,"ciudad":"Cuyutlán","sug":"Miguel Hidalgo","conf":100,"vec":"Miguel Hidalgo","celda":"38929","visto":"2026-07-24"},"182790322":{"id":182790322,"lat":18.888633,"lon":-103.878881,"rt":1,"ciudad":"Tecomán","sug":"Luis Spota","conf":100,"vec":"Juan Jose Arreola","celda":"38932","visto":"2026-07-24"},"182790295":{"id":182790295,"lat":18.889307,"lon":-103.881994,"rt":1,"ciudad":"Tecomán","sug":"Juan José Arreola","conf":100,"vec":"De Los Maestros","celda":"38932","visto":"2026-07-24"},"182790296":{"id":182790296,"lat":18.888793,"lon":-103.880556,"rt":1,"ciudad":"Tecomán","sug":"Juan José Arreola","conf":100,"vec":"Melquíades Ruvalcaba","celda":"38932","visto":"2026-07-24"},"182787091":{"id":182787091,"lat":18.888298,"lon":-103.879114,"rt":1,"ciudad":"Tecomán","sug":"Juan José Arreola","conf":100,"vec":"Anselmo Villalobos","celda":"38932","visto":"2026-07-24"},"458819144":{"id":458819144,"lat":18.888298,"lon":-103.879114,"rt":1,"ciudad":"","sug":"Luis Spota","conf":100,"vec":"","celda":"38932","visto":"2026-07-24"},"458819143":{"id":458819143,"lat":18.887348,"lon":-103.879709,"rt":1,"ciudad":"","sug":"Luis Spota","conf":100,"vec":"","celda":"38932","visto":"2026-07-24"},"206336429":{"id":206336429,"lat":18.897089,"lon":-103.893801,"rt":1,"ciudad":"","sug":"Crisantemo","conf":100,"vec":"Río Bravo","celda":"38932","visto":"2026-07-24"},"276683812":{"id":276683812,"lat":18.886888,"lon":-103.634414,"rt":1,"ciudad":"Las Conchas","sug":"Crispín Gutiérrez Moreno","conf":100,"vec":"Ing Crispin Gutierrez Moreno","celda":"38936","visto":"2026-07-24"},"276683794":{"id":276683794,"lat":18.886197,"lon":-103.634699,"rt":1,"ciudad":"Las Conchas","sug":"Crispín Gutiérrez Moreno","conf":100,"vec":"Ing Crispin Gutierrez Moreno","celda":"38936","visto":"2026-07-24"},"251742005":{"id":251742005,"lat":18.956106,"lon":-103.949324,"rt":1,"ciudad":"Cofradía de Juárez","sug":"Los Pinos","conf":100,"vec":"Nardo","celda":"39461","visto":"2026-07-24"},"251740125":{"id":251740125,"lat":18.968484,"lon":-103.957146,"rt":1,"ciudad":"","sug":"Manuel Acuña","conf":100,"vec":"Ignacio Comonfort","celda":"39461","visto":"2026-07-24"},"251740124":{"id":251740124,"lat":18.968032,"lon":-103.957084,"rt":1,"ciudad":"","sug":"Manuel Acuña","conf":100,"vec":"Independencia","celda":"39461","visto":"2026-07-24"},"251743882":{"id":251743882,"lat":18.957262,"lon":-103.951958,"rt":1,"ciudad":"Cofradía de Juárez","sug":"Piscila","conf":100,"vec":"Carlos Cruz Mendoza","celda":"39461","visto":"2026-07-24"},"251380745":{"id":251380745,"lat":18.9494,"lon":-103.945847,"rt":1,"ciudad":"","sug":"Boca del Río","conf":100,"vec":"Independencia","celda":"39461","visto":"2026-07-24"},"251380748":{"id":251380748,"lat":18.950547,"lon":-103.945461,"rt":1,"ciudad":"","sug":"Boca del Río","conf":100,"vec":"Lázaro Cárdenas","celda":"39461","visto":"2026-07-24"},"251741359":{"id":251741359,"lat":18.951986,"lon":-103.948717,"rt":1,"ciudad":"","sug":"Pihuamo","conf":100,"vec":"","celda":"39461","visto":"2026-07-24"},"251741358":{"id":251741358,"lat":18.951397,"lon":-103.94905,"rt":1,"ciudad":"","sug":"Corregidora","conf":100,"vec":"5 de Febrero","celda":"39461","visto":"2026-07-24"},"249370558":{"id":249370558,"lat":18.996237,"lon":-103.880137,"rt":1,"ciudad":"Caleras","sug":"Revolución","conf":100,"vec":"16 de Septiembre","celda":"39462","visto":"2026-07-24"},"249370713":{"id":249370713,"lat":18.998555,"lon":-103.87947,"rt":1,"ciudad":"Caleras","sug":"Revolución","conf":100,"vec":"Miguel Hidalgo","celda":"39462","visto":"2026-07-24"},"249370714":{"id":249370714,"lat":18.99938,"lon":-103.879249,"rt":1,"ciudad":"Caleras","sug":"Revolución","conf":100,"vec":"Miguel Hidalgo","celda":"39462","visto":"2026-07-24"},"249370675":{"id":249370675,"lat":18.99709,"lon":-103.879869,"rt":1,"ciudad":"Caleras","sug":"Revolución","conf":100,"vec":"5 de Febrero","celda":"39462","visto":"2026-07-24"},"249370665":{"id":249370665,"lat":18.997046,"lon":-103.879885,"rt":1,"ciudad":"Caleras","sug":"Revolución","conf":100,"vec":"Independencia","celda":"39462","visto":"2026-07-24"},"274264692":{"id":274264692,"lat":18.995551,"lon":-103.736975,"rt":1,"ciudad":"","sug":"Benito Juárez","conf":100,"vec":"Benito Juarez","celda":"39465","visto":"2026-07-24"},"276688651":{"id":276688651,"lat":18.999547,"lon":-103.733273,"rt":1,"ciudad":"Ixtlahuacán","sug":"Fernando Moreno Peña","conf":100,"vec":"Cuauhtémoc","celda":"39465","visto":"2026-07-24"},"423825366":{"id":423825366,"lat":18.994871,"lon":-103.735821,"rt":1,"ciudad":"","sug":"Rodolfo Chávez Carrillo","conf":100,"vec":"Pedro Torres Ortiz","celda":"39465","visto":"2026-07-24"},"341177239":{"id":341177239,"lat":18.99829,"lon":-103.734116,"rt":1,"ciudad":"Ixtlahuacán","sug":"De los Melones","conf":100,"vec":"De los Melones","celda":"39465","visto":"2026-07-24"},"276165353":{"id":276165353,"lat":18.974292,"lon":-103.534078,"rt":1,"ciudad":"","sug":"Luis Echeverría Álvarez","conf":100,"vec":"Pablo Silva García","celda":"39468","visto":"2026-07-24"},"276165354":{"id":276165354,"lat":18.974339,"lon":-103.534178,"rt":1,"ciudad":"","sug":"Luis Echeverría Álvarez","conf":100,"vec":"Pablo Silva García","celda":"39468","visto":"2026-07-24"},"181893811":{"id":181893811,"lat":19.02158,"lon":-104.325031,"rt":1,"ciudad":"Manzanillo","sug":"Sardinas","conf":100,"vec":"Orquideas","celda":"39985","visto":"2026-07-24"},"258484185":{"id":258484185,"lat":19.025256,"lon":-104.324911,"rt":1,"ciudad":"Manzanillo","sug":"De las Amapolas","conf":100,"vec":"Av. Rosas","celda":"39985","visto":"2026-07-24"},"256216311":{"id":256216311,"lat":19.048876,"lon":-104.318897,"rt":2,"ciudad":"","sug":"Belisario Domínguez","conf":100,"vec":"Francisco I. Madero","celda":"39985","visto":"2026-07-24"},"181896346":{"id":181896346,"lat":19.025014,"lon":-104.324497,"rt":1,"ciudad":"Manzanillo","sug":"Nardos","conf":100,"vec":"Av. Rosas","celda":"39985","visto":"2026-07-24"},"181896274":{"id":181896274,"lat":19.025739,"lon":-104.325747,"rt":1,"ciudad":"Manzanillo","sug":"De las Magnolias","conf":100,"vec":"Calz. de las Flores","celda":"39985","visto":"2026-07-24"},"181896265":{"id":181896265,"lat":19.025995,"lon":-104.326189,"rt":1,"ciudad":"Manzanillo","sug":"Gardenias","conf":100,"vec":"Calz. de las Flores","celda":"39985","visto":"2026-07-24"},"258484637":{"id":258484637,"lat":19.023922,"lon":-104.322248,"rt":1,"ciudad":"Manzanillo","sug":"De las Flores","conf":100,"vec":"","celda":"39985","visto":"2026-07-24"},"258484356":{"id":258484356,"lat":19.021612,"lon":-104.328478,"rt":1,"ciudad":"Manzanillo","sug":"San Agustín","conf":100,"vec":"","celda":"39985","visto":"2026-07-24"},"258484357":{"id":258484357,"lat":19.020673,"lon":-104.327536,"rt":1,"ciudad":"Manzanillo","sug":"San Agustín","conf":100,"vec":"","celda":"39985","visto":"2026-07-24"},"179220143":{"id":179220143,"lat":19.058185,"lon":-104.233013,"rt":1,"ciudad":"","sug":"Pavoreal","conf":100,"vec":"","celda":"39986","visto":"2026-07-24"},"179220158":{"id":179220158,"lat":19.057993,"lon":-104.230988,"rt":1,"ciudad":"","sug":"Quetzal","conf":100,"vec":"","celda":"39986","visto":"2026-07-24"},"179220156":{"id":179220156,"lat":19.058155,"lon":-104.231358,"rt":1,"ciudad":"","sug":"Guacamaya","conf":100,"vec":"","celda":"39986","visto":"2026-07-24"},"179220154":{"id":179220154,"lat":19.058151,"lon":-104.230971,"rt":1,"ciudad":"","sug":"Quetzal","conf":100,"vec":"","celda":"39986","visto":"2026-07-24"},"179220150":{"id":179220150,"lat":19.057517,"lon":-104.232032,"rt":1,"ciudad":"","sug":"Golondrinas","conf":100,"vec":"","celda":"39986","visto":"2026-07-24"},"179220149":{"id":179220149,"lat":19.05817,"lon":-104.232017,"rt":1,"ciudad":"","sug":"Golondrinas","conf":100,"vec":"","celda":"39986","visto":"2026-07-24"},"179220147":{"id":179220147,"lat":19.05818,"lon":-104.232442,"rt":1,"ciudad":"","sug":"Guacamaya","conf":100,"vec":"","celda":"39986","visto":"2026-07-24"},"179220144":{"id":179220144,"lat":19.057572,"lon":-104.233017,"rt":1,"ciudad":"","sug":"Pavoreal","conf":100,"vec":"","celda":"39986","visto":"2026-07-24"},"179220110":{"id":179220110,"lat":19.058819,"lon":-104.232844,"rt":1,"ciudad":"","sug":"Colibrí","conf":100,"vec":"","celda":"39986","visto":"2026-07-24"},"179220106":{"id":179220106,"lat":19.05882,"lon":-104.23301,"rt":1,"ciudad":"","sug":"Colibrí","conf":100,"vec":"","celda":"39986","visto":"2026-07-24"},"179220114":{"id":179220114,"lat":19.058799,"lon":-104.230258,"rt":1,"ciudad":"","sug":"Colibrí","conf":100,"vec":"","celda":"39986","visto":"2026-07-24"},"179220112":{"id":179220112,"lat":19.058824,"lon":-104.231235,"rt":1,"ciudad":"","sug":"Colibrí","conf":100,"vec":"","celda":"39986","visto":"2026-07-24"},"179220174":{"id":179220174,"lat":19.056883,"lon":-104.230998,"rt":1,"ciudad":"","sug":"Quetzal","conf":100,"vec":"Albatros","celda":"39986","visto":"2026-07-24"},"179220175":{"id":179220175,"lat":19.056235,"lon":-104.231004,"rt":1,"ciudad":"","sug":"Quetzal","conf":100,"vec":"Albatros","celda":"39986","visto":"2026-07-24"},"179220171":{"id":179220171,"lat":19.05546,"lon":-104.23101,"rt":1,"ciudad":"","sug":"Quetzal","conf":100,"vec":"Ruiseñor","celda":"39986","visto":"2026-07-24"},"179220166":{"id":179220166,"lat":19.056237,"lon":-104.232056,"rt":1,"ciudad":"","sug":"Golondrinas","conf":100,"vec":"Albatros","celda":"39986","visto":"2026-07-24"},"179220167":{"id":179220167,"lat":19.055479,"lon":-104.232071,"rt":1,"ciudad":"","sug":"Golondrinas","conf":100,"vec":"Ruiseñor","celda":"39986","visto":"2026-07-24"},"179220162":{"id":179220162,"lat":19.056883,"lon":-104.232044,"rt":1,"ciudad":"","sug":"Golondrinas","conf":100,"vec":"Albatros","celda":"39986","visto":"2026-07-24"},"179220160":{"id":179220160,"lat":19.057506,"lon":-104.231165,"rt":1,"ciudad":"","sug":"Gaviota","conf":100,"vec":"","celda":"39986","visto":"2026-07-24"},"179220188":{"id":179220188,"lat":19.058145,"lon":-104.230467,"rt":1,"ciudad":"","sug":"Guacamaya","conf":100,"vec":"","celda":"39986","visto":"2026-07-24"},"179220189":{"id":179220189,"lat":19.058115,"lon":-104.229416,"rt":1,"ciudad":"","sug":"Guacamaya","conf":100,"vec":"","celda":"39987","visto":"2026-07-24"},"179220186":{"id":179220186,"lat":19.058126,"lon":-104.229828,"rt":1,"ciudad":"","sug":"Garza","conf":100,"vec":"","celda":"39987","visto":"2026-07-24"},"179220187":{"id":179220187,"lat":19.057485,"lon":-104.229848,"rt":1,"ciudad":"","sug":"Garza","conf":100,"vec":"","celda":"39987","visto":"2026-07-24"},"179220184":{"id":179220184,"lat":19.057506,"lon":-104.23051,"rt":1,"ciudad":"","sug":"Gaviota","conf":100,"vec":"","celda":"39986","visto":"2026-07-24"},"179220183":{"id":179220183,"lat":19.057415,"lon":-104.229851,"rt":1,"ciudad":"","sug":"Garza","conf":100,"vec":"Ruiseñor","celda":"39987","visto":"2026-07-24"},"179220179":{"id":179220179,"lat":19.056167,"lon":-104.229893,"rt":1,"ciudad":"","sug":"Garza","conf":100,"vec":"Ruiseñor","celda":"39987","visto":"2026-07-24"},"179219982":{"id":179219982,"lat":19.056938,"lon":-104.233023,"rt":1,"ciudad":"","sug":"Pavoreal","conf":100,"vec":"Albatros","celda":"39986","visto":"2026-07-24"},"179219980":{"id":179219980,"lat":19.057557,"lon":-104.232629,"rt":1,"ciudad":"","sug":"Gaviota","conf":100,"vec":"","celda":"39986","visto":"2026-07-24"},"179070863":{"id":179070863,"lat":19.053294,"lon":-104.244122,"rt":1,"ciudad":"","sug":"Del Sol","conf":100,"vec":"Constelación","celda":"39986","visto":"2026-07-24"},"179263368":{"id":179263368,"lat":19.05435,"lon":-104.228206,"rt":1,"ciudad":"","sug":"Ópalo","conf":100,"vec":"","celda":"39987","visto":"2026-07-24"},"179263363":{"id":179263363,"lat":19.054421,"lon":-104.227983,"rt":1,"ciudad":"","sug":"Safiro","conf":100,"vec":"","celda":"39987","visto":"2026-07-24"},"179220378":{"id":179220378,"lat":19.05437,"lon":-104.229407,"rt":1,"ciudad":"","sug":"Ópalo","conf":100,"vec":"","celda":"39987","visto":"2026-07-24"},"179220377":{"id":179220377,"lat":19.054669,"lon":-104.229461,"rt":1,"ciudad":"","sug":"Alejadrina","conf":100,"vec":"","celda":"39987","visto":"2026-07-24"},"179262414":{"id":179262414,"lat":19.053782,"lon":-104.228294,"rt":1,"ciudad":"","sug":"Acerinas","conf":100,"vec":"","celda":"39987","visto":"2026-07-24"},"179220423":{"id":179220423,"lat":19.05437,"lon":-104.228967,"rt":1,"ciudad":"","sug":"Ópalo","conf":100,"vec":"","celda":"39987","visto":"2026-07-24"},"179220417":{"id":179220417,"lat":19.05438,"lon":-104.228914,"rt":1,"ciudad":"","sug":"Rubí","conf":100,"vec":"","celda":"39987","visto":"2026-07-24"},"179262428":{"id":179262428,"lat":19.055227,"lon":-104.227632,"rt":1,"ciudad":"","sug":"Agua Marina","conf":100,"vec":"","celda":"39987","visto":"2026-07-24"},"179262427":{"id":179262427,"lat":19.055227,"lon":-104.228203,"rt":1,"ciudad":"","sug":"Agua Marina","conf":100,"vec":"","celda":"39987","visto":"2026-07-24"},"179220443":{"id":179220443,"lat":19.05434,"lon":-104.228506,"rt":1,"ciudad":"","sug":"Ópalo","conf":100,"vec":"","celda":"39987","visto":"2026-07-24"},"179220440":{"id":179220440,"lat":19.054343,"lon":-104.228397,"rt":1,"ciudad":"","sug":"Acerinas","conf":100,"vec":"","celda":"39987","visto":"2026-07-24"},"179220441":{"id":179220441,"lat":19.055227,"lon":-104.228667,"rt":1,"ciudad":"","sug":"Agua Marina","conf":100,"vec":"","celda":"39987","visto":"2026-07-24"},"179220260":{"id":179220260,"lat":19.056388,"lon":-104.228729,"rt":1,"ciudad":"","sug":"Pelicanos","conf":100,"vec":"Ruiseñor","celda":"39987","visto":"2026-07-24"},"179220261":{"id":179220261,"lat":19.055729,"lon":-104.228745,"rt":1,"ciudad":"","sug":"Pelicanos","conf":100,"vec":"Ruiseñor","celda":"39987","visto":"2026-07-24"},"179070828":{"id":179070828,"lat":19.05298,"lon":-104.244567,"rt":1,"ciudad":"","sug":"Del Sol","conf":100,"vec":"Del Sol","celda":"39986","visto":"2026-07-24"},"179262328":{"id":179262328,"lat":19.054092,"lon":-104.228841,"rt":1,"ciudad":"","sug":"Rubí","conf":100,"vec":"","celda":"39987","visto":"2026-07-24"},"179071002":{"id":179071002,"lat":19.054067,"lon":-104.244075,"rt":1,"ciudad":"","sug":"Géminis","conf":100,"vec":"Fénix","celda":"39986","visto":"2026-07-24"},"179071003":{"id":179071003,"lat":19.053806,"lon":-104.243715,"rt":1,"ciudad":"","sug":"Géminis","conf":100,"vec":"Escorpión","celda":"39986","visto":"2026-07-24"},"179219939":{"id":179219939,"lat":19.055497,"lon":-104.233037,"rt":1,"ciudad":"","sug":"Pavoreal","conf":100,"vec":"Ruiseñor","celda":"39986","visto":"2026-07-24"},"179219961":{"id":179219961,"lat":19.056233,"lon":-104.23303,"rt":1,"ciudad":"","sug":"Pavoreal","conf":100,"vec":"Albatros","celda":"39986","visto":"2026-07-24"},"179269983":{"id":179269983,"lat":19.055237,"lon":-104.229498,"rt":1,"ciudad":"","sug":"Agua Marina","conf":100,"vec":"","celda":"39987","visto":"2026-07-24"},"179269982":{"id":179269982,"lat":19.055293,"lon":-104.229675,"rt":1,"ciudad":"","sug":"Agua Marina","conf":100,"vec":"MEX-200 / Manzanillo - Tecomán","celda":"39987","visto":"2026-07-24"},"179265709":{"id":179265709,"lat":19.055909,"lon":-104.222527,"rt":1,"ciudad":"","sug":"Trinidad Guerrero Zamora","conf":100,"vec":"","celda":"39987","visto":"2026-07-24"},"179265708":{"id":179265708,"lat":19.056462,"lon":-104.222806,"rt":1,"ciudad":"","sug":"Trinidad Guerrero Zamora","conf":100,"vec":"","celda":"39987","visto":"2026-07-24"},"179265704":{"id":179265704,"lat":19.056668,"lon":-104.222307,"rt":1,"ciudad":"","sug":"Cástulo Hernández","conf":100,"vec":"","celda":"39987","visto":"2026-07-24"},"179265703":{"id":179265703,"lat":19.056486,"lon":-104.222818,"rt":1,"ciudad":"","sug":"Cástulo Hernández","conf":100,"vec":"","celda":"39987","visto":"2026-07-24"},"179265698":{"id":179265698,"lat":19.056486,"lon":-104.222818,"rt":1,"ciudad":"","sug":"Trinidad Guerrero Zamora","conf":100,"vec":"","celda":"39987","visto":"2026-07-24"},"179265726":{"id":179265726,"lat":19.055251,"lon":-104.222826,"rt":1,"ciudad":"","sug":"Manuel Martínez Farías","conf":100,"vec":"","celda":"39987","visto":"2026-07-24"},"179265724":{"id":179265724,"lat":19.055991,"lon":-104.223133,"rt":1,"ciudad":"","sug":"Manuel Martínez Farías","conf":100,"vec":"","celda":"39987","visto":"2026-07-24"},"179265722":{"id":179265722,"lat":19.055861,"lon":-104.222691,"rt":1,"ciudad":"","sug":"Benito Rincón","conf":100,"vec":"","celda":"39987","visto":"2026-07-24"},"179264441":{"id":179264441,"lat":19.055192,"lon":-104.222959,"rt":1,"ciudad":"","sug":"Cándido Melgoza","conf":100,"vec":"","celda":"39987","visto":"2026-07-24"},"179263369":{"id":179263369,"lat":19.054329,"lon":-104.227546,"rt":1,"ciudad":"","sug":"Ópalo","conf":100,"vec":"","celda":"39987","visto":"2026-07-24"},"179265691":{"id":179265691,"lat":19.057139,"lon":-104.222817,"rt":1,"ciudad":"","sug":"Antonio Santana","conf":100,"vec":"","celda":"39987","visto":"2026-07-24"},"179263898":{"id":179263898,"lat":19.054594,"lon":-104.22415,"rt":1,"ciudad":"","sug":"Cándido Melgoza","conf":100,"vec":"MEX-200 / Manzanillo - Tecomán","celda":"39987","visto":"2026-07-24"},"179266287":{"id":179266287,"lat":19.056188,"lon":-104.226552,"rt":1,"ciudad":"","sug":"Gorrion","conf":100,"vec":"Ruiseñor","celda":"39987","visto":"2026-07-24"},"179265279":{"id":179265279,"lat":19.055422,"lon":-104.224011,"rt":1,"ciudad":"","sug":"Juan Cervantes Álvarez","conf":100,"vec":"","celda":"39987","visto":"2026-07-24"},"179264763":{"id":179264763,"lat":19.054878,"lon":-104.223506,"rt":1,"ciudad":"","sug":"Cándido Melgoza","conf":100,"vec":"","celda":"39987","visto":"2026-07-24"},"179266293":{"id":179266293,"lat":19.055896,"lon":-104.227624,"rt":1,"ciudad":"","sug":"Cardenal","conf":100,"vec":"Ruiseñor","celda":"39987","visto":"2026-07-24"},"179266292":{"id":179266292,"lat":19.056847,"lon":-104.227662,"rt":1,"ciudad":"","sug":"Cardenal","conf":100,"vec":"Ruiseñor","celda":"39987","visto":"2026-07-24"},"179266288":{"id":179266288,"lat":19.055377,"lon":-104.226544,"rt":1,"ciudad":"","sug":"Gorrion","conf":100,"vec":"Ruiseñor","celda":"39987","visto":"2026-07-24"},"179265743":{"id":179265743,"lat":19.055443,"lon":-104.22346,"rt":1,"ciudad":"","sug":"Nepomuceno Montes Farías","conf":100,"vec":"","celda":"39987","visto":"2026-07-24"},"179265731":{"id":179265731,"lat":19.055666,"lon":-104.223291,"rt":1,"ciudad":"","sug":"Benito Rincón","conf":100,"vec":"","celda":"39987","visto":"2026-07-24"},"179265729":{"id":179265729,"lat":19.055567,"lon":-104.223597,"rt":1,"ciudad":"","sug":"Benito Rincón","conf":100,"vec":"","celda":"39987","visto":"2026-07-24"},"179264470":{"id":179264470,"lat":19.055466,"lon":-104.222337,"rt":1,"ciudad":"","sug":"Cándido Melgoza","conf":100,"vec":"","celda":"39987","visto":"2026-07-24"},"179264768":{"id":179264768,"lat":19.056216,"lon":-104.221392,"rt":1,"ciudad":"","sug":"Cándido Melgoza","conf":100,"vec":"","celda":"39987","visto":"2026-07-24"},"179265280":{"id":179265280,"lat":19.055124,"lon":-104.223879,"rt":1,"ciudad":"","sug":"Juan Cervantes Álvarez","conf":100,"vec":"","celda":"39987","visto":"2026-07-24"},"179267444":{"id":179267444,"lat":19.05719,"lon":-104.218367,"rt":1,"ciudad":"","sug":"Francisco Velasco Curiel","conf":100,"vec":"","celda":"39987","visto":"2026-07-24"},"179267153":{"id":179267153,"lat":19.056432,"lon":-104.223922,"rt":1,"ciudad":"","sug":"Nepomuceno Montes Farías","conf":100,"vec":"","celda":"39987","visto":"2026-07-24"},"179267152":{"id":179267152,"lat":19.057497,"lon":-104.224706,"rt":1,"ciudad":"","sug":"Nepomuceno Montes Farías","conf":100,"vec":"","celda":"39987","visto":"2026-07-24"},"272034797":{"id":272034797,"lat":19.017045,"lon":-104.160532,"rt":1,"ciudad":"San Buenaventura","sug":"Morelos","conf":100,"vec":"Niños Heroes","celda":"39988","visto":"2026-07-24"},"272055745":{"id":272055745,"lat":19.014121,"lon":-104.120557,"rt":1,"ciudad":"Ejido Nuevo Cuyutlán","sug":"Armería","conf":100,"vec":"Vicente Guerrero","celda":"39988","visto":"2026-07-24"},"272055744":{"id":272055744,"lat":19.015014,"lon":-104.120614,"rt":1,"ciudad":"Ejido Nuevo Cuyutlán","sug":"Armería","conf":100,"vec":"Vicente Guerrero","celda":"39988","visto":"2026-07-24"},"316931863":{"id":316931863,"lat":19.011308,"lon":-104.094103,"rt":2,"ciudad":"Santa Rita","sug":"Morelos","conf":100,"vec":"Tecomán","celda":"39989","visto":"2026-07-24"},"316933138":{"id":316933138,"lat":19.012303,"lon":-104.094143,"rt":2,"ciudad":"Santa Rita","sug":"Morelos","conf":100,"vec":"Colima","celda":"39989","visto":"2026-07-24"},"316931866":{"id":316931866,"lat":19.012303,"lon":-104.094143,"rt":2,"ciudad":"Santa Rita","sug":"Morelos","conf":100,"vec":"Tecomán","celda":"39989","visto":"2026-07-24"},"268658819":{"id":268658819,"lat":19.019167,"lon":-104.005243,"rt":1,"ciudad":"Augusto Gómez Villanueva (Coalatilla)","sug":"Licenciado Antonio Salazar","conf":100,"vec":"","celda":"39990","visto":"2026-07-24"},"268658817":{"id":268658817,"lat":19.020927,"lon":-104.006096,"rt":1,"ciudad":"Augusto Gómez Villanueva (Coalatilla)","sug":"29 de Octubre","conf":100,"vec":"","celda":"39990","visto":"2026-07-24"},"268659073":{"id":268659073,"lat":19.016244,"lon":-104.000874,"rt":1,"ciudad":"Augusto Gómez Villanueva (Coalatilla)","sug":"Jesús González","conf":100,"vec":"","celda":"39990","visto":"2026-07-24"},"268659072":{"id":268659072,"lat":19.016663,"lon":-104.000956,"rt":1,"ciudad":"Augusto Gómez Villanueva (Coalatilla)","sug":"Jesús González","conf":100,"vec":"","celda":"39990","visto":"2026-07-24"},"268658823":{"id":268658823,"lat":19.019197,"lon":-104.005069,"rt":1,"ciudad":"Augusto Gómez Villanueva (Coalatilla)","sug":"México","conf":100,"vec":"Ing. Manuel González","celda":"39990","visto":"2026-07-24"},"268659079":{"id":268659079,"lat":19.017453,"lon":-103.999943,"rt":1,"ciudad":"Augusto Gómez Villanueva (Coalatilla)","sug":"Estefano E. Cherzi","conf":100,"vec":"","celda":"39990","visto":"2026-07-24"},"268658182":{"id":268658182,"lat":19.021571,"lon":-104.000088,"rt":1,"ciudad":"Augusto Gómez Villanueva (Coalatilla)","sug":"Ingeniero Manuel González","conf":100,"vec":"Estefano E. Cherzi","celda":"39990","visto":"2026-07-24"},"268658822":{"id":268658822,"lat":19.020147,"lon":-104.005264,"rt":1,"ciudad":"Augusto Gómez Villanueva (Coalatilla)","sug":"México","conf":100,"vec":"Ing. Manuel González","celda":"39990","visto":"2026-07-24"},"268659078":{"id":268659078,"lat":19.017052,"lon":-103.999611,"rt":1,"ciudad":"Augusto Gómez Villanueva (Coalatilla)","sug":"Estefano E. Cherzi","conf":100,"vec":"","celda":"39990","visto":"2026-07-24"},"268658185":{"id":268658185,"lat":19.020019,"lon":-104.00075,"rt":1,"ciudad":"Augusto Gómez Villanueva (Coalatilla)","sug":"Licenciado Antonio Salazar","conf":100,"vec":"","celda":"39990","visto":"2026-07-24"},"268658184":{"id":268658184,"lat":19.020496,"lon":-104.000845,"rt":1,"ciudad":"","sug":"Estefano E. Cherzi","conf":100,"vec":"Estefano E. Cherzi","celda":"39990","visto":"2026-07-24"},"268658319":{"id":268658319,"lat":19.018925,"lon":-104.001694,"rt":1,"ciudad":"","sug":"Armería","conf":100,"vec":"Prof Pablo Silva","celda":"39990","visto":"2026-07-24"},"268658446":{"id":268658446,"lat":19.021559,"lon":-104.002864,"rt":1,"ciudad":"Augusto Gómez Villanueva (Coalatilla)","sug":"29 de Octubre","conf":100,"vec":"","celda":"39990","visto":"2026-07-24"},"268658317":{"id":268658317,"lat":19.018976,"lon":-104.001395,"rt":1,"ciudad":"","sug":"Armería","conf":100,"vec":"","celda":"39990","visto":"2026-07-24"},"268658322":{"id":268658322,"lat":19.019848,"lon":-104.001593,"rt":1,"ciudad":"Augusto Gómez Villanueva (Coalatilla)","sug":"Jesús González","conf":100,"vec":"","celda":"39990","visto":"2026-07-24"},"268658321":{"id":268658321,"lat":19.018976,"lon":-104.001395,"rt":1,"ciudad":"Augusto Gómez Villanueva (Coalatilla)","sug":"Jesús González","conf":100,"vec":"","celda":"39990","visto":"2026-07-24"},"268658198":{"id":268658198,"lat":19.019116,"lon":-104.000571,"rt":1,"ciudad":"Augusto Gómez Villanueva (Coalatilla)","sug":"Armería","conf":100,"vec":"","celda":"39990","visto":"2026-07-24"},"268658459":{"id":268658459,"lat":19.020766,"lon":-104.002691,"rt":1,"ciudad":"Augusto Gómez Villanueva (Coalatilla)","sug":"Profesor Pablo Silva","conf":100,"vec":"Ing. Manuel González","celda":"39990","visto":"2026-07-24"},"268658714":{"id":268658714,"lat":19.018706,"lon":-104.007634,"rt":1,"ciudad":"Augusto Gómez Villanueva (Coalatilla)","sug":"La Atarjea","conf":100,"vec":"Ing. Manuel González","celda":"39990","visto":"2026-07-24"},"268658201":{"id":268658201,"lat":19.020019,"lon":-104.00075,"rt":1,"ciudad":"","sug":"Estefano E. Cherzi","conf":100,"vec":"","celda":"39990","visto":"2026-07-24"},"268658713":{"id":268658713,"lat":19.019646,"lon":-104.007842,"rt":1,"ciudad":"Augusto Gómez Villanueva (Coalatilla)","sug":"La Atarjea","conf":100,"vec":"Ing. Manuel González","celda":"39990","visto":"2026-07-24"},"270084153":{"id":270084153,"lat":19.021866,"lon":-104.001139,"rt":1,"ciudad":"Augusto Gómez Villanueva (Coalatilla)","sug":"29 de Octubre","conf":100,"vec":"Estefano E. Cherzi","celda":"39990","visto":"2026-07-24"},"268658722":{"id":268658722,"lat":19.018706,"lon":-104.007634,"rt":1,"ciudad":"Augusto Gómez Villanueva (Coalatilla)","sug":"Licenciado Antonio Salazar","conf":100,"vec":"","celda":"39990","visto":"2026-07-24"},"270084154":{"id":270084154,"lat":19.02171,"lon":-104.002015,"rt":1,"ciudad":"Augusto Gómez Villanueva (Coalatilla)","sug":"29 de Octubre","conf":100,"vec":"Estefano E. Cherzi","celda":"39990","visto":"2026-07-24"},"268658725":{"id":268658725,"lat":19.019807,"lon":-104.007015,"rt":1,"ciudad":"Augusto Gómez Villanueva (Coalatilla)","sug":"Cristo Rey","conf":100,"vec":"Ing. Manuel González","celda":"39990","visto":"2026-07-24"},"268658866":{"id":268658866,"lat":19.021145,"lon":-104.0049,"rt":1,"ciudad":"Augusto Gómez Villanueva (Coalatilla)","sug":"29 de Octubre","conf":100,"vec":"","celda":"39990","visto":"2026-07-24"},"268658487":{"id":268658487,"lat":19.019671,"lon":-104.002496,"rt":1,"ciudad":"Augusto Gómez Villanueva (Coalatilla)","sug":"Licenciado Antonio Salazar","conf":100,"vec":"Prof Pablo Silva","celda":"39990","visto":"2026-07-24"},"268658871":{"id":268658871,"lat":19.020304,"lon":-104.004407,"rt":1,"ciudad":"Augusto Gómez Villanueva (Coalatilla)","sug":"Coatan","conf":100,"vec":"Ing. Manuel González","celda":"39990","visto":"2026-07-24"},"268658868":{"id":268658868,"lat":19.019197,"lon":-104.005069,"rt":1,"ciudad":"Augusto Gómez Villanueva (Coalatilla)","sug":"Licenciado Antonio Salazar","conf":100,"vec":"","celda":"39990","visto":"2026-07-24"},"268658872":{"id":268658872,"lat":19.019345,"lon":-104.004216,"rt":1,"ciudad":"Augusto Gómez Villanueva (Coalatilla)","sug":"Coatan","conf":100,"vec":"Ing. Manuel González","celda":"39990","visto":"2026-07-24"},"268658620":{"id":268658620,"lat":19.019491,"lon":-104.008644,"rt":1,"ciudad":"Augusto Gómez Villanueva (Coalatilla)","sug":"Arroyo del Salto","conf":100,"vec":"Ing. Manuel González","celda":"39990","visto":"2026-07-24"},"270084176":{"id":270084176,"lat":19.023225,"lon":-104.002359,"rt":1,"ciudad":"Augusto Gómez Villanueva (Coalatilla)","sug":"Jesús González","conf":100,"vec":"","celda":"39990","visto":"2026-07-24"},"270084169":{"id":270084169,"lat":19.022809,"lon":-104.001342,"rt":1,"ciudad":"Augusto Gómez Villanueva (Coalatilla)","sug":"Pedro Rivera","conf":100,"vec":"Estefano E. Cherzi","celda":"39990","visto":"2026-07-24"},"270084175":{"id":270084175,"lat":19.022635,"lon":-104.002225,"rt":1,"ciudad":"Augusto Gómez Villanueva (Coalatilla)","sug":"Jesús González","conf":100,"vec":"","celda":"39990","visto":"2026-07-24"},"268658907":{"id":268658907,"lat":19.019503,"lon":-104.003358,"rt":1,"ciudad":"Augusto Gómez Villanueva (Coalatilla)","sug":"Licenciado Antonio Salazar","conf":100,"vec":"Prof Pablo Silva","celda":"39990","visto":"2026-07-24"},"268658783":{"id":268658783,"lat":19.018848,"lon":-104.006821,"rt":1,"ciudad":"Augusto Gómez Villanueva (Coalatilla)","sug":"Licenciado Antonio Salazar","conf":100,"vec":"","celda":"39990","visto":"2026-07-24"},"268658908":{"id":268658908,"lat":19.019416,"lon":-104.003806,"rt":1,"ciudad":"Augusto Gómez Villanueva (Coalatilla)","sug":"Licenciado Antonio Salazar","conf":100,"vec":"","celda":"39990","visto":"2026-07-24"},"268658787":{"id":268658787,"lat":19.019033,"lon":-104.005904,"rt":1,"ciudad":"Augusto Gómez Villanueva (Coalatilla)","sug":"Pirámide","conf":100,"vec":"Ing. Manuel González","celda":"39990","visto":"2026-07-24"},"268658915":{"id":268658915,"lat":19.021403,"lon":-104.003739,"rt":1,"ciudad":"Augusto Gómez Villanueva (Coalatilla)","sug":"29 de Octubre","conf":100,"vec":"","celda":"39990","visto":"2026-07-24"},"268658914":{"id":268658914,"lat":19.020459,"lon":-104.003549,"rt":1,"ciudad":"Augusto Gómez Villanueva (Coalatilla)","sug":"Ramiro Zavala","conf":100,"vec":"Ing. Manuel González","celda":"39990","visto":"2026-07-24"},"268658913":{"id":268658913,"lat":19.021403,"lon":-104.003739,"rt":1,"ciudad":"Augusto Gómez Villanueva (Coalatilla)","sug":"Ramiro Zavala","conf":100,"vec":"","celda":"39990","visto":"2026-07-24"},"268658912":{"id":268658912,"lat":19.019503,"lon":-104.003358,"rt":1,"ciudad":"Augusto Gómez Villanueva (Coalatilla)","sug":"Ramiro Zavala","conf":100,"vec":"Ing. Manuel González","celda":"39990","visto":"2026-07-24"},"268658791":{"id":268658791,"lat":19.01998,"lon":-104.006124,"rt":1,"ciudad":"Augusto Gómez Villanueva (Coalatilla)","sug":"Pirámide","conf":100,"vec":"Ing. Manuel González","celda":"39990","visto":"2026-07-24"},"268658789":{"id":268658789,"lat":19.020851,"lon":-104.006724,"rt":1,"ciudad":"Augusto Gómez Villanueva (Coalatilla)","sug":"29 de Octubre","conf":100,"vec":"","celda":"39990","visto":"2026-07-24"},"268658916":{"id":268658916,"lat":19.021353,"lon":-104.00402,"rt":1,"ciudad":"Augusto Gómez Villanueva (Coalatilla)","sug":"29 de Octubre","conf":100,"vec":"","celda":"39990","visto":"2026-07-24"},"268659044":{"id":268659044,"lat":19.018117,"lon":-104.000373,"rt":1,"ciudad":"Augusto Gómez Villanueva (Coalatilla)","sug":"Estefano E. Cherzi","conf":100,"vec":"","celda":"39990","visto":"2026-07-24"},"268658280":{"id":268658280,"lat":19.02171,"lon":-104.002015,"rt":1,"ciudad":"Augusto Gómez Villanueva (Coalatilla)","sug":"Jesús González","conf":100,"vec":"Ing. Manuel González","celda":"39990","visto":"2026-07-24"},"268658285":{"id":268658285,"lat":19.019953,"lon":-104.001054,"rt":1,"ciudad":"Augusto Gómez Villanueva (Coalatilla)","sug":"Licenciado Antonio Salazar","conf":100,"vec":"","celda":"39990","visto":"2026-07-24"},"268658284":{"id":268658284,"lat":19.020782,"lon":-104.001805,"rt":1,"ciudad":"Augusto Gómez Villanueva (Coalatilla)","sug":"Jesús González","conf":100,"vec":"Ing. Manuel González","celda":"39990","visto":"2026-07-24"},"270084328":{"id":270084328,"lat":19.025269,"lon":-104.001018,"rt":1,"ciudad":"Augusto Gómez Villanueva (Coalatilla)","sug":"de la Cruz","conf":100,"vec":"","celda":"39990","visto":"2026-07-24"},"268658934":{"id":268658934,"lat":19.019116,"lon":-104.000571,"rt":1,"ciudad":"Augusto Gómez Villanueva (Coalatilla)","sug":"Estefano E. Cherzi","conf":100,"vec":"","celda":"39990","visto":"2026-07-24"},"268658938":{"id":268658938,"lat":19.017777,"lon":-104.00211,"rt":1,"ciudad":"Augusto Gómez Villanueva (Coalatilla)","sug":"Cesáreo Muñiz Sosa","conf":100,"vec":"Prof Pablo Silva","celda":"39990","visto":"2026-07-24"},"268658937":{"id":268658937,"lat":19.017953,"lon":-104.001211,"rt":1,"ciudad":"Augusto Gómez Villanueva (Coalatilla)","sug":"Cesáreo Muñiz Sosa","conf":100,"vec":"","celda":"39990","visto":"2026-07-24"},"270084327":{"id":270084327,"lat":19.024816,"lon":-104.000904,"rt":1,"ciudad":"Augusto Gómez Villanueva (Coalatilla)","sug":"de la Cruz","conf":100,"vec":"","celda":"39990","visto":"2026-07-24"},"268659068":{"id":268659068,"lat":19.017294,"lon":-104.001081,"rt":1,"ciudad":"Augusto Gómez Villanueva (Coalatilla)","sug":"Jesús González","conf":100,"vec":"","celda":"39990","visto":"2026-07-24"},"475056815":{"id":475056815,"lat":19.055555,"lon":-103.934577,"rt":1,"ciudad":"","sug":"5 de Mayo","conf":100,"vec":"Benito Juárez","celda":"39991","visto":"2026-07-24"},"276686687":{"id":276686687,"lat":19.001004,"lon":-103.734378,"rt":1,"ciudad":"Ixtlahuacán","sug":"Arroyo Seco","conf":100,"vec":"Torres Quintero","celda":"39995","visto":"2026-07-24"},"276688652":{"id":276688652,"lat":19.000202,"lon":-103.733218,"rt":1,"ciudad":"Ixtlahuacán","sug":"Fernando Moreno Peña","conf":100,"vec":"Cuauhtémoc","celda":"39995","visto":"2026-07-24"},"276688581":{"id":276688581,"lat":19.003403,"lon":-103.734731,"rt":1,"ciudad":"Ixtlahuacán","sug":"Arroyo Seco","conf":100,"vec":"Maclovio Herrera","celda":"39995","visto":"2026-07-24"},"269681596":{"id":269681596,"lat":19.086634,"lon":-104.300653,"rt":2,"ciudad":"Manzanillo","sug":"Licenciado Miguel de la Madrid Hurtado","conf":100,"vec":"Blvd. Miguel de la Madrid Hurtado","celda":"40515","visto":"2026-07-24"},"240975451":{"id":240975451,"lat":19.109844,"lon":-104.261616,"rt":1,"ciudad":"","sug":"Licenciado Nabor Ochoa López","conf":100,"vec":"MEX-98 / Manzanillo - Minatitlán","celda":"40516","visto":"2026-07-24"},"260917146":{"id":260917146,"lat":19.122525,"lon":-104.265228,"rt":1,"ciudad":"Jalipa","sug":"Av. Colima","conf":100,"vec":"16 de septiembre","celda":"41046","visto":"2026-07-24"},"260921130":{"id":260921130,"lat":19.115664,"lon":-104.271504,"rt":1,"ciudad":"Jalipa","sug":"Quetzal","conf":100,"vec":"Av. Lázaro Cárdenas","celda":"40516","visto":"2026-07-24"},"260916623":{"id":260916623,"lat":19.12176,"lon":-104.267808,"rt":1,"ciudad":"Jalipa","sug":"Doctor Miguel Galindo","conf":100,"vec":"Av. Lázaro Cárdenas","celda":"41046","visto":"2026-07-24"},"260924811":{"id":260924811,"lat":19.121286,"lon":-104.270706,"rt":1,"ciudad":"Jalipa","sug":"Adolfo López Mateos","conf":100,"vec":"","celda":"41046","visto":"2026-07-24"},"260924804":{"id":260924804,"lat":19.120783,"lon":-104.269902,"rt":1,"ciudad":"Jalipa","sug":"Av. José María Morelos","conf":100,"vec":"","celda":"41046","visto":"2026-07-24"},"260924820":{"id":260924820,"lat":19.120783,"lon":-104.269902,"rt":1,"ciudad":"Jalipa","sug":"Adolfo López Mateos","conf":100,"vec":"Francisco Lopez Madero","celda":"41046","visto":"2026-07-24"},"260916631":{"id":260916631,"lat":19.121141,"lon":-104.266689,"rt":1,"ciudad":"Jalipa","sug":"Doctor Miguel Galindo","conf":100,"vec":"Emiliano Zapata","celda":"41046","visto":"2026-07-24"},"260916627":{"id":260916627,"lat":19.121449,"lon":-104.267245,"rt":1,"ciudad":"Jalipa","sug":"Doctor Miguel Galindo","conf":100,"vec":"Av. Lázaro Cárdenas","celda":"41046","visto":"2026-07-24"},"260924863":{"id":260924863,"lat":19.120455,"lon":-104.269377,"rt":1,"ciudad":"Jalipa","sug":"Adolfo López Mateos","conf":100,"vec":"Av. Lázaro Cárdenas","celda":"41046","visto":"2026-07-24"},"260924889":{"id":260924889,"lat":19.119432,"lon":-104.267741,"rt":1,"ciudad":"Jalipa","sug":"Adolfo López Mateos","conf":100,"vec":"Benito Juárez","celda":"40516","visto":"2026-07-24"},"260924890":{"id":260924890,"lat":19.119767,"lon":-104.268276,"rt":1,"ciudad":"Jalipa","sug":"Adolfo López Mateos","conf":100,"vec":"Benito Juárez","celda":"40516","visto":"2026-07-24"},"260924880":{"id":260924880,"lat":19.120096,"lon":-104.268804,"rt":1,"ciudad":"Jalipa","sug":"Adolfo López Mateos","conf":100,"vec":"Emiliano Zapata","celda":"41046","visto":"2026-07-24"},"260924694":{"id":260924694,"lat":19.119988,"lon":-104.2674,"rt":1,"ciudad":"Jalipa","sug":"Libertad","conf":100,"vec":"Emiliano Zapata","celda":"40516","visto":"2026-07-24"},"260924706":{"id":260924706,"lat":19.120414,"lon":-104.268094,"rt":1,"ciudad":"Jalipa","sug":"Libertad","conf":100,"vec":"Av. Lázaro Cárdenas","celda":"41046","visto":"2026-07-24"},"260924767":{"id":260924767,"lat":19.120973,"lon":-104.26906,"rt":1,"ciudad":"Jalipa","sug":"Libertad","conf":100,"vec":"Francisco Lopez Madero","celda":"41046","visto":"2026-07-24"},"260924766":{"id":260924766,"lat":19.121288,"lon":-104.269604,"rt":1,"ciudad":"Jalipa","sug":"Libertad","conf":100,"vec":"","celda":"41046","visto":"2026-07-24"},"260924755":{"id":260924755,"lat":19.120638,"lon":-104.26848,"rt":1,"ciudad":"Jalipa","sug":"Libertad","conf":100,"vec":"Francisco Lopez Madero","celda":"41046","visto":"2026-07-24"},"260924784":{"id":260924784,"lat":19.121507,"lon":-104.269475,"rt":1,"ciudad":"Jalipa","sug":"Av. José María Morelos","conf":100,"vec":"","celda":"41046","visto":"2026-07-24"},"240975275":{"id":240975275,"lat":19.107943,"lon":-104.259293,"rt":1,"ciudad":"","sug":"Licenciado Nabor Ochoa López","conf":100,"vec":"","celda":"40516","visto":"2026-07-24"},"260917514":{"id":260917514,"lat":19.121216,"lon":-104.268134,"rt":1,"ciudad":"Jalipa","sug":"Vicente Guerrero","conf":100,"vec":"Emiliano Zapata","celda":"41046","visto":"2026-07-24"},"260917507":{"id":260917507,"lat":19.121521,"lon":-104.268724,"rt":1,"ciudad":"Jalipa","sug":"Vicente Guerrero","conf":100,"vec":"Av. Lázaro Cárdenas","celda":"41046","visto":"2026-07-24"},"260917521":{"id":260917521,"lat":19.120924,"lon":-104.267567,"rt":1,"ciudad":"Jalipa","sug":"Vicente Guerrero","conf":100,"vec":"Benito Juárez","celda":"41046","visto":"2026-07-24"},"260917520":{"id":260917520,"lat":19.120633,"lon":-104.267002,"rt":1,"ciudad":"Jalipa","sug":"Vicente Guerrero","conf":100,"vec":"Benito Juárez","celda":"41046","visto":"2026-07-24"},"271187707":{"id":271187707,"lat":19.119234,"lon":-104.268603,"rt":1,"ciudad":"Jalipa","sug":"Gustavo Díaz Ordaz","conf":100,"vec":"Av. Lázaro Cárdenas","celda":"40516","visto":"2026-07-24"},"271187711":{"id":271187711,"lat":19.119553,"lon":-104.269129,"rt":1,"ciudad":"Jalipa","sug":"Gustavo Díaz Ordaz","conf":100,"vec":"Francisco Lopez Madero","celda":"40516","visto":"2026-07-24"},"271187703":{"id":271187703,"lat":19.119015,"lon":-104.268244,"rt":1,"ciudad":"Jalipa","sug":"Gustavo Díaz Ordaz","conf":100,"vec":"Emiliano Zapata","celda":"40516","visto":"2026-07-24"},"271187757":{"id":271187757,"lat":19.118107,"lon":-104.269996,"rt":1,"ciudad":"Jalipa","sug":"Carrillo Puerto","conf":100,"vec":"Francisco Lopez Madero","celda":"40516","visto":"2026-07-24"},"271187759":{"id":271187759,"lat":19.118439,"lon":-104.270613,"rt":1,"ciudad":"Jalipa","sug":"Carrillo Puerto","conf":100,"vec":"Francisco Lopez Madero","celda":"40516","visto":"2026-07-24"},"271187744":{"id":271187744,"lat":19.118357,"lon":-104.268407,"rt":1,"ciudad":"Jalipa","sug":"Manuel Ávila Camacho","conf":100,"vec":"Benito Juárez","celda":"40516","visto":"2026-07-24"},"271187746":{"id":271187746,"lat":19.118679,"lon":-104.268943,"rt":1,"ciudad":"Jalipa","sug":"Manuel Ávila Camacho","conf":100,"vec":"Benito Juárez","celda":"40516","visto":"2026-07-24"},"271187751":{"id":271187751,"lat":19.119358,"lon":-104.270049,"rt":1,"ciudad":"Jalipa","sug":"Manuel Ávila Camacho","conf":100,"vec":"Av. Lázaro Cárdenas","celda":"40516","visto":"2026-07-24"},"271187750":{"id":271187750,"lat":19.118914,"lon":-104.269333,"rt":1,"ciudad":"Jalipa","sug":"Manuel Ávila Camacho","conf":100,"vec":"Emiliano Zapata","celda":"40516","visto":"2026-07-24"},"271187760":{"id":271187760,"lat":19.118739,"lon":-104.271171,"rt":1,"ciudad":"Jalipa","sug":"Av. José María Morelos","conf":100,"vec":"Manuel Álvarez","celda":"40516","visto":"2026-07-24"},"271187763":{"id":271187763,"lat":19.117594,"lon":-104.271827,"rt":1,"ciudad":"Jalipa","sug":"Av. José María Morelos","conf":100,"vec":"","celda":"40516","visto":"2026-07-24"},"271187762":{"id":271187762,"lat":19.118625,"lon":-104.271237,"rt":1,"ciudad":"Jalipa","sug":"Av. José María Morelos","conf":100,"vec":"","celda":"40516","visto":"2026-07-24"},"271187767":{"id":271187767,"lat":19.118182,"lon":-104.271491,"rt":1,"ciudad":"Jalipa","sug":"Adolfo de la Huerta","conf":100,"vec":"Francisco Lopez Madero","celda":"40516","visto":"2026-07-24"},"271187766":{"id":271187766,"lat":19.11788,"lon":-104.270955,"rt":1,"ciudad":"Jalipa","sug":"Adolfo de la Huerta","conf":100,"vec":"Av. Lázaro Cárdenas","celda":"40516","visto":"2026-07-24"},"271187720":{"id":271187720,"lat":19.119203,"lon":-104.270898,"rt":1,"ciudad":"Jalipa","sug":"Manuel Álvarez","conf":100,"vec":"","celda":"40516","visto":"2026-07-24"},"271187723":{"id":271187723,"lat":19.119604,"lon":-104.270663,"rt":1,"ciudad":"Jalipa","sug":"Av. José María Morelos","conf":100,"vec":"","celda":"40516","visto":"2026-07-24"},"271187722":{"id":271187722,"lat":19.119699,"lon":-104.270599,"rt":1,"ciudad":"Jalipa","sug":"Av. José María Morelos","conf":100,"vec":"","celda":"40516","visto":"2026-07-24"},"271187727":{"id":271187727,"lat":19.119699,"lon":-104.270599,"rt":1,"ciudad":"Jalipa","sug":"Manuel Ávila Camacho","conf":100,"vec":"Francisco Lopez Madero","celda":"40516","visto":"2026-07-24"},"271187715":{"id":271187715,"lat":19.119907,"lon":-104.269713,"rt":1,"ciudad":"Jalipa","sug":"Gustavo Díaz Ordaz","conf":100,"vec":"Francisco Lopez Madero","celda":"40516","visto":"2026-07-24"},"271187716":{"id":271187716,"lat":19.120412,"lon":-104.270121,"rt":1,"ciudad":"Jalipa","sug":"Av. José María Morelos","conf":100,"vec":"","celda":"41046","visto":"2026-07-24"},"271187736":{"id":271187736,"lat":19.118407,"lon":-104.26937,"rt":1,"ciudad":"Jalipa","sug":"Manuel Álvarez","conf":100,"vec":"Av. Lázaro Cárdenas","celda":"40516","visto":"2026-07-24"},"271187741":{"id":271187741,"lat":19.117307,"lon":-104.267627,"rt":1,"ciudad":"Jalipa","sug":"Manuel Álvarez","conf":100,"vec":"Benito Juárez","celda":"40516","visto":"2026-07-24"},"271187740":{"id":271187740,"lat":19.117957,"lon":-104.268657,"rt":1,"ciudad":"Jalipa","sug":"Manuel Álvarez","conf":100,"vec":"Emiliano Zapata","celda":"40516","visto":"2026-07-24"},"271187732":{"id":271187732,"lat":19.11891,"lon":-104.270324,"rt":1,"ciudad":"Jalipa","sug":"Manuel Álvarez","conf":100,"vec":"Francisco Lopez Madero","celda":"40516","visto":"2026-07-24"},"271187734":{"id":271187734,"lat":19.118706,"lon":-104.269923,"rt":1,"ciudad":"Jalipa","sug":"Manuel Álvarez","conf":100,"vec":"Francisco Lopez Madero","celda":"40516","visto":"2026-07-24"},"260917500":{"id":260917500,"lat":19.121818,"lon":-104.269302,"rt":1,"ciudad":"Jalipa","sug":"Av. José María Morelos","conf":100,"vec":"","celda":"41046","visto":"2026-07-24"},"260917503":{"id":260917503,"lat":19.121818,"lon":-104.269302,"rt":1,"ciudad":"Jalipa","sug":"Vicente Guerrero","conf":100,"vec":"Francisco Lopez Madero","celda":"41046","visto":"2026-07-24"},"260917496":{"id":260917496,"lat":19.121955,"lon":-104.269566,"rt":1,"ciudad":"Jalipa","sug":"Vicente Guerrero","conf":100,"vec":"","celda":"41046","visto":"2026-07-24"},"271637596":{"id":271637596,"lat":19.090297,"lon":-103.875815,"rt":1,"ciudad":"","sug":"Central Madrid","conf":100,"vec":"","celda":"40522","visto":"2026-07-24"},"271637597":{"id":271637597,"lat":19.090622,"lon":-103.87533,"rt":1,"ciudad":"","sug":"M. E. Espinoza","conf":100,"vec":"","celda":"40522","visto":"2026-07-24"},"271636659":{"id":271636659,"lat":19.086875,"lon":-103.875184,"rt":1,"ciudad":"Madrid","sug":"Perú","conf":100,"vec":"Revolución","celda":"40522","visto":"2026-07-24"},"271637643":{"id":271637643,"lat":19.090493,"lon":-103.876149,"rt":1,"ciudad":"","sug":"Central Madrid","conf":100,"vec":"","celda":"40522","visto":"2026-07-24"},"271637645":{"id":271637645,"lat":19.091192,"lon":-103.876228,"rt":1,"ciudad":"","sug":"Unión 93","conf":100,"vec":"","celda":"40522","visto":"2026-07-24"},"271636696":{"id":271636696,"lat":19.086764,"lon":-103.874534,"rt":1,"ciudad":"Madrid","sug":"Haití","conf":100,"vec":"Revolución","celda":"40522","visto":"2026-07-24"},"271614583":{"id":271614583,"lat":19.081589,"lon":-103.867546,"rt":1,"ciudad":"Madrid","sug":"Enrique O. de la Madrid","conf":100,"vec":"Honduras","celda":"40523","visto":"2026-07-24"},"271614587":{"id":271614587,"lat":19.082608,"lon":-103.867144,"rt":1,"ciudad":"Madrid","sug":"Enrique O. de la Madrid","conf":100,"vec":"México","celda":"40523","visto":"2026-07-24"},"271615298":{"id":271615298,"lat":19.084837,"lon":-103.866315,"rt":1,"ciudad":"Madrid","sug":"Enrique O. de la Madrid","conf":100,"vec":"Manuel Álvarez","celda":"40523","visto":"2026-07-24"},"271615299":{"id":271615299,"lat":19.083894,"lon":-103.866676,"rt":1,"ciudad":"Madrid","sug":"Enrique O. de la Madrid","conf":100,"vec":"El Salvador","celda":"40523","visto":"2026-07-24"},"271614592":{"id":271614592,"lat":19.082951,"lon":-103.867023,"rt":1,"ciudad":"Madrid","sug":"Enrique O. de la Madrid","conf":100,"vec":"México","celda":"40523","visto":"2026-07-24"},"249558751":{"id":249558751,"lat":19.118646,"lon":-103.773305,"rt":1,"ciudad":"Los Asmoles","sug":"Ignacio Allende","conf":100,"vec":"","celda":"40524","visto":"2026-07-24"},"249558749":{"id":249558749,"lat":19.118646,"lon":-103.773305,"rt":1,"ciudad":"Los Asmoles","sug":"Emiliano Zapata","conf":100,"vec":"","celda":"40524","visto":"2026-07-24"},"249558993":{"id":249558993,"lat":19.122266,"lon":-103.772969,"rt":1,"ciudad":"Los Asmoles","sug":"Miguel Hidalgo","conf":100,"vec":"","celda":"41054","visto":"2026-07-24"},"249558990":{"id":249558990,"lat":19.121839,"lon":-103.774342,"rt":1,"ciudad":"Los Asmoles","sug":"20 de Noviembre","conf":100,"vec":"","celda":"41054","visto":"2026-07-24"},"249558988":{"id":249558988,"lat":19.121252,"lon":-103.773391,"rt":1,"ciudad":"Los Asmoles","sug":"José María Morelos","conf":100,"vec":"","celda":"41054","visto":"2026-07-24"},"249558986":{"id":249558986,"lat":19.121558,"lon":-103.775161,"rt":1,"ciudad":"Los Asmoles","sug":"20 de Noviembre","conf":100,"vec":"","celda":"41054","visto":"2026-07-24"},"249558984":{"id":249558984,"lat":19.12262,"lon":-103.774596,"rt":1,"ciudad":"Los Asmoles","sug":"Ignacio Allende","conf":100,"vec":"","celda":"41054","visto":"2026-07-24"},"249558983":{"id":249558983,"lat":19.121839,"lon":-103.774342,"rt":1,"ciudad":"Los Asmoles","sug":"Ignacio Allende","conf":100,"vec":"","celda":"41054","visto":"2026-07-24"},"249558976":{"id":249558976,"lat":19.120697,"lon":-103.775208,"rt":1,"ciudad":"Los Asmoles","sug":"Pino Suárez","conf":100,"vec":"","celda":"41054","visto":"2026-07-24"},"249558756":{"id":249558756,"lat":19.118838,"lon":-103.772627,"rt":1,"ciudad":"Los Asmoles","sug":"Emiliano Zapata","conf":100,"vec":"","celda":"40524","visto":"2026-07-24"},"249558755":{"id":249558755,"lat":19.11906,"lon":-103.771909,"rt":1,"ciudad":"Los Asmoles","sug":"Emiliano Zapata","conf":100,"vec":"MEX-110 / Paso por Los Asmoles","celda":"40524","visto":"2026-07-24"},"249558806":{"id":249558806,"lat":19.119469,"lon":-103.773572,"rt":1,"ciudad":"Los Asmoles","sug":"Ignacio Allende","conf":100,"vec":"","celda":"40524","visto":"2026-07-24"},"249558803":{"id":249558803,"lat":19.118838,"lon":-103.772627,"rt":1,"ciudad":"Los Asmoles","sug":"José María Morelos","conf":100,"vec":"","celda":"40524","visto":"2026-07-24"},"249558798":{"id":249558798,"lat":19.119905,"lon":-103.772188,"rt":1,"ciudad":"Los Asmoles","sug":"Miguel Hidalgo","conf":100,"vec":"","celda":"40524","visto":"2026-07-24"},"249558972":{"id":249558972,"lat":19.121252,"lon":-103.773391,"rt":1,"ciudad":"Los Asmoles","sug":"Pino Suárez","conf":100,"vec":"","celda":"41054","visto":"2026-07-24"},"249558971":{"id":249558971,"lat":19.12146,"lon":-103.772702,"rt":1,"ciudad":"Los Asmoles","sug":"Pino Suárez","conf":100,"vec":"MEX-110 / Paso por Los Asmoles","celda":"41054","visto":"2026-07-24"},"249558969":{"id":249558969,"lat":19.12146,"lon":-103.772702,"rt":1,"ciudad":"Los Asmoles","sug":"Miguel Hidalgo","conf":100,"vec":"","celda":"41054","visto":"2026-07-24"},"249558968":{"id":249558968,"lat":19.120448,"lon":-103.773137,"rt":1,"ciudad":"Los Asmoles","sug":"José María Morelos","conf":100,"vec":"","celda":"41054","visto":"2026-07-24"},"249558966":{"id":249558966,"lat":19.121042,"lon":-103.774084,"rt":1,"ciudad":"Los Asmoles","sug":"Pino Suárez","conf":100,"vec":"","celda":"41054","visto":"2026-07-24"},"249558963":{"id":249558963,"lat":19.121042,"lon":-103.774084,"rt":1,"ciudad":"Los Asmoles","sug":"Ignacio Allende","conf":100,"vec":"","celda":"41054","visto":"2026-07-24"},"249558959":{"id":249558959,"lat":19.120657,"lon":-103.772437,"rt":1,"ciudad":"Los Asmoles","sug":"Miguel Hidalgo","conf":100,"vec":"","celda":"41054","visto":"2026-07-24"},"249558958":{"id":249558958,"lat":19.120892,"lon":-103.771652,"rt":1,"ciudad":"Los Asmoles","sug":"Francisco I. Madero","conf":100,"vec":"MEX-110 / Paso por Los Asmoles","celda":"41054","visto":"2026-07-24"},"249558957":{"id":249558957,"lat":19.120657,"lon":-103.772437,"rt":1,"ciudad":"Los Asmoles","sug":"Francisco I. Madero","conf":100,"vec":"","celda":"41054","visto":"2026-07-24"},"249558955":{"id":249558955,"lat":19.120448,"lon":-103.773137,"rt":1,"ciudad":"Los Asmoles","sug":"Francisco I. Madero","conf":100,"vec":"","celda":"41054","visto":"2026-07-24"},"249558954":{"id":249558954,"lat":19.119683,"lon":-103.772895,"rt":1,"ciudad":"Los Asmoles","sug":"José María Morelos","conf":100,"vec":"","celda":"40524","visto":"2026-07-24"},"249558951":{"id":249558951,"lat":19.120242,"lon":-103.773823,"rt":1,"ciudad":"Los Asmoles","sug":"Ignacio Allende","conf":100,"vec":"","celda":"41054","visto":"2026-07-24"},"249558949":{"id":249558949,"lat":19.119928,"lon":-103.774873,"rt":1,"ciudad":"Los Asmoles","sug":"Francisco I. Madero","conf":100,"vec":"MEX-110 / Colima - Entronque Tecomán","celda":"40524","visto":"2026-07-24"},"333303213":{"id":333303213,"lat":19.114374,"lon":-103.731664,"rt":1,"ciudad":"Los Ortices","sug":"Colegio Militar","conf":100,"vec":"Juan de la Barrera","celda":"40525","visto":"2026-07-24"},"271988876":{"id":271988876,"lat":19.113451,"lon":-103.734584,"rt":1,"ciudad":"Los Ortices","sug":"Benito Juárez","conf":100,"vec":"Francisco Márquez","celda":"40525","visto":"2026-07-24"},"271988875":{"id":271988875,"lat":19.114282,"lon":-103.734469,"rt":1,"ciudad":"Los Ortices","sug":"Benito Juárez","conf":100,"vec":"Francisco Márquez","celda":"40525","visto":"2026-07-24"},"271988938":{"id":271988938,"lat":19.113634,"lon":-103.731817,"rt":1,"ciudad":"Los Ortices","sug":"Colegio Militar","conf":100,"vec":"Francisco Márquez","celda":"40525","visto":"2026-07-24"},"275975439":{"id":275975439,"lat":19.095468,"lon":-103.624048,"rt":1,"ciudad":"Los Tepames","sug":"Vicente Guerrero","conf":100,"vec":"Vicente Guerrero","celda":"40527","visto":"2026-07-24"},"260828035":{"id":260828035,"lat":19.144019,"lon":-104.337316,"rt":1,"ciudad":"Manzanillo","sug":"Miltonea","conf":100,"vec":"Orquideas","celda":"41045","visto":"2026-07-24"},"260828034":{"id":260828034,"lat":19.144227,"lon":-104.338398,"rt":1,"ciudad":"Manzanillo","sug":"Miltonea","conf":100,"vec":"Orquideas","celda":"41045","visto":"2026-07-24"},"260828050":{"id":260828050,"lat":19.143348,"lon":-104.337557,"rt":1,"ciudad":"Manzanillo","sug":"Vanda","conf":100,"vec":"Orquideas","celda":"41045","visto":"2026-07-24"},"260828021":{"id":260828021,"lat":19.144369,"lon":-104.337241,"rt":1,"ciudad":"Manzanillo","sug":"Cattleya","conf":100,"vec":"Orquideas","celda":"41045","visto":"2026-07-24"},"260828020":{"id":260828020,"lat":19.144581,"lon":-104.338326,"rt":1,"ciudad":"Manzanillo","sug":"Cattleya","conf":100,"vec":"Orquideas","celda":"41045","visto":"2026-07-24"},"260827682":{"id":260827682,"lat":19.144851,"lon":-104.337579,"rt":1,"ciudad":"Manzanillo","sug":"Mandrágora","conf":100,"vec":"Roble","celda":"41045","visto":"2026-07-24"},"260827681":{"id":260827681,"lat":19.145269,"lon":-104.337561,"rt":1,"ciudad":"Manzanillo","sug":"Mandrágora","conf":100,"vec":"Azucena","celda":"41045","visto":"2026-07-24"},"260827621":{"id":260827621,"lat":19.143222,"lon":-104.33874,"rt":1,"ciudad":"Manzanillo","sug":"Pleione","conf":100,"vec":"Rosas","celda":"41045","visto":"2026-07-24"},"260825688":{"id":260825688,"lat":19.148063,"lon":-104.344595,"rt":1,"ciudad":"Manzanillo","sug":"Mar Egeo","conf":100,"vec":"Océanos Atlantico","celda":"41045","visto":"2026-07-24"},"260825692":{"id":260825692,"lat":19.14846,"lon":-104.344558,"rt":1,"ciudad":"Manzanillo","sug":"Mar Egeo","conf":100,"vec":"Océano Atlantico","celda":"41045","visto":"2026-07-24"},"260825702":{"id":260825702,"lat":19.148354,"lon":-104.343294,"rt":1,"ciudad":"Manzanillo","sug":"Mar Rojo","conf":100,"vec":"Océano Atlantico","celda":"41045","visto":"2026-07-24"},"260825700":{"id":260825700,"lat":19.14796,"lon":-104.343334,"rt":1,"ciudad":"Manzanillo","sug":"Mar Rojo","conf":100,"vec":"Océano Atlantico","celda":"41045","visto":"2026-07-24"},"338344515":{"id":338344515,"lat":19.170848,"lon":-104.346194,"rt":1,"ciudad":"Manzanillo","sug":"Flor de Lis","conf":100,"vec":"","celda":"41045","visto":"2026-07-24"},"338344512":{"id":338344512,"lat":19.170848,"lon":-104.346194,"rt":1,"ciudad":"Manzanillo","sug":"Ixora","conf":100,"vec":"","celda":"41045","visto":"2026-07-24"},"338344517":{"id":338344517,"lat":19.170713,"lon":-104.346155,"rt":1,"ciudad":"Manzanillo","sug":"Flor de Lis","conf":100,"vec":"Av. Jacaranda","celda":"41045","visto":"2026-07-24"},"260848604":{"id":260848604,"lat":19.12781,"lon":-104.264446,"rt":1,"ciudad":"Jalipa","sug":"Ignacio Zaragoza","conf":100,"vec":"Av. Lázaro Cárdenas","celda":"41046","visto":"2026-07-24"},"260914653":{"id":260914653,"lat":19.124771,"lon":-104.266763,"rt":1,"ciudad":"Jalipa","sug":"Ejido","conf":100,"vec":"Av. Lázaro Cárdenas","celda":"41046","visto":"2026-07-24"},"260914649":{"id":260914649,"lat":19.125092,"lon":-104.267328,"rt":1,"ciudad":"Jalipa","sug":"Ejido","conf":100,"vec":"Francisco Lopez Madero","celda":"41046","visto":"2026-07-24"},"260914644":{"id":260914644,"lat":19.125092,"lon":-104.267328,"rt":1,"ciudad":"Jalipa","sug":"Av. José María Morelos","conf":100,"vec":"","celda":"41046","visto":"2026-07-24"},"260914647":{"id":260914647,"lat":19.125986,"lon":-104.268969,"rt":1,"ciudad":"Jalipa","sug":"Ejido","conf":100,"vec":"","celda":"41046","visto":"2026-07-24"},"260848620":{"id":260848620,"lat":19.127092,"lon":-104.264464,"rt":1,"ciudad":"Jalipa","sug":"Guadalupe Victoria","conf":100,"vec":"Av. Lázaro Cárdenas","celda":"41046","visto":"2026-07-24"},"260914659":{"id":260914659,"lat":19.124444,"lon":-104.266186,"rt":1,"ciudad":"Jalipa","sug":"Ejido","conf":100,"vec":"Emiliano Zapata","celda":"41046","visto":"2026-07-24"},"260915170":{"id":260915170,"lat":19.124535,"lon":-104.267655,"rt":1,"ciudad":"Jalipa","sug":"Av. José María Morelos","conf":100,"vec":"Niños Heroes","celda":"41046","visto":"2026-07-24"},"260913661":{"id":260913661,"lat":19.125305,"lon":-104.266441,"rt":1,"ciudad":"Jalipa","sug":"Josefa Ortiz de Domínguez","conf":100,"vec":"Av. Lázaro Cárdenas","celda":"41046","visto":"2026-07-24"},"260913657":{"id":260913657,"lat":19.125609,"lon":-104.267002,"rt":1,"ciudad":"Jalipa","sug":"Josefa Ortiz de Domínguez","conf":100,"vec":"Francisco Lopez Madero","celda":"41046","visto":"2026-07-24"},"260913653":{"id":260913653,"lat":19.126543,"lon":-104.268722,"rt":1,"ciudad":"Jalipa","sug":"Josefa Ortiz de Domínguez","conf":100,"vec":"","celda":"41046","visto":"2026-07-24"},"260913654":{"id":260913654,"lat":19.125609,"lon":-104.267002,"rt":1,"ciudad":"Jalipa","sug":"Av. José María Morelos","conf":100,"vec":"","celda":"41046","visto":"2026-07-24"},"260848404":{"id":260848404,"lat":19.12628,"lon":-104.264308,"rt":1,"ciudad":"Jalipa","sug":"Pedro Nuñez","conf":100,"vec":"Av. Lázaro Cárdenas","celda":"41046","visto":"2026-07-24"},"260848405":{"id":260848405,"lat":19.126129,"lon":-104.263981,"rt":1,"ciudad":"Jalipa","sug":"Pedro Nuñez","conf":100,"vec":"Emiliano Zapata","celda":"41046","visto":"2026-07-24"},"260848421":{"id":260848421,"lat":19.127131,"lon":-104.266112,"rt":1,"ciudad":"Jalipa","sug":"Pedro Nuñez","conf":100,"vec":"","celda":"41046","visto":"2026-07-24"},"260848422":{"id":260848422,"lat":19.126824,"lon":-104.265502,"rt":1,"ciudad":"Jalipa","sug":"Pedro Nuñez","conf":100,"vec":"Av. Lázaro Cárdenas","celda":"41046","visto":"2026-07-24"},"260847952":{"id":260847952,"lat":19.125205,"lon":-104.264954,"rt":2,"ciudad":"Jalipa","sug":"Álvaro Obregón","conf":100,"vec":"Benito Juárez","celda":"41046","visto":"2026-07-24"},"260847953":{"id":260847953,"lat":19.125505,"lon":-104.265527,"rt":2,"ciudad":"Jalipa","sug":"Álvaro Obregón","conf":100,"vec":"Emiliano Zapata","celda":"41046","visto":"2026-07-24"},"260848481":{"id":260848481,"lat":19.12491,"lon":-104.264389,"rt":2,"ciudad":"Jalipa","sug":"Álvaro Obregón","conf":100,"vec":"Benito Juárez","celda":"41046","visto":"2026-07-24"},"260848846":{"id":260848846,"lat":19.125935,"lon":-104.264996,"rt":1,"ciudad":"Jalipa","sug":"Cuauhtémoc","conf":100,"vec":"Av. Lázaro Cárdenas","celda":"41046","visto":"2026-07-24"},"260848842":{"id":260848842,"lat":19.125447,"lon":-104.264061,"rt":1,"ciudad":"Jalipa","sug":"Cuauhtémoc","conf":100,"vec":"Emiliano Zapata","celda":"41046","visto":"2026-07-24"},"260848838":{"id":260848838,"lat":19.12523,"lon":-104.263644,"rt":1,"ciudad":"Jalipa","sug":"Cuauhtémoc","conf":100,"vec":"Benito Juárez","celda":"41046","visto":"2026-07-24"},"260848852":{"id":260848852,"lat":19.126124,"lon":-104.266684,"rt":1,"ciudad":"Jalipa","sug":"Av. José María Morelos","conf":100,"vec":"","celda":"41046","visto":"2026-07-24"},"260848853":{"id":260848853,"lat":19.126129,"lon":-104.266693,"rt":1,"ciudad":"Jalipa","sug":"Álvaro Obregón","conf":100,"vec":"","celda":"41046","visto":"2026-07-24"},"260848850":{"id":260848850,"lat":19.126394,"lon":-104.266052,"rt":1,"ciudad":"Jalipa","sug":"Cuauhtémoc","conf":100,"vec":"Av. Lázaro Cárdenas","celda":"41046","visto":"2026-07-24"},"260848851":{"id":260848851,"lat":19.126578,"lon":-104.266406,"rt":1,"ciudad":"Jalipa","sug":"Av. José María Morelos","conf":100,"vec":"","celda":"41046","visto":"2026-07-24"},"260848355":{"id":260848355,"lat":19.126124,"lon":-104.266684,"rt":1,"ciudad":"Jalipa","sug":"Álvaro Obregón","conf":100,"vec":"Francisco Lopez Madero","celda":"41046","visto":"2026-07-24"},"260913677":{"id":260913677,"lat":19.124671,"lon":-104.265275,"rt":1,"ciudad":"Jalipa","sug":"Josefa Ortiz de Domínguez","conf":100,"vec":"Benito Juárez","celda":"41046","visto":"2026-07-24"},"260913667":{"id":260913667,"lat":19.124984,"lon":-104.265851,"rt":1,"ciudad":"Jalipa","sug":"Josefa Ortiz de Domínguez","conf":100,"vec":"Emiliano Zapata","celda":"41046","visto":"2026-07-24"},"260913684":{"id":260913684,"lat":19.124368,"lon":-104.264717,"rt":1,"ciudad":"Jalipa","sug":"Josefa Ortiz de Domínguez","conf":100,"vec":"Benito Juárez","celda":"41046","visto":"2026-07-24"},"260913687":{"id":260913687,"lat":19.124666,"lon":-104.263923,"rt":1,"ciudad":"Jalipa","sug":"Av. Colima","conf":100,"vec":"Av. Colima","celda":"41046","visto":"2026-07-24"},"260848146":{"id":260848146,"lat":19.125826,"lon":-104.266127,"rt":1,"ciudad":"Jalipa","sug":"Álvaro Obregón","conf":100,"vec":"Av. Lázaro Cárdenas","celda":"41046","visto":"2026-07-24"},"260848766":{"id":260848766,"lat":19.124885,"lon":-104.263775,"rt":1,"ciudad":"Jalipa","sug":"Av. Colima","conf":100,"vec":"","celda":"41046","visto":"2026-07-24"},"268750087":{"id":268750087,"lat":19.167165,"lon":-103.933401,"rt":1,"ciudad":"Pueblo Juárez (La Magdalena)","sug":"Belisario Domínguez","conf":100,"vec":"","celda":"41051","visto":"2026-07-24"},"268750080":{"id":268750080,"lat":19.167913,"lon":-103.932878,"rt":1,"ciudad":"Pueblo Juárez (La Magdalena)","sug":"Venustiano Carranza","conf":100,"vec":"Mariano Matamoros","celda":"41051","visto":"2026-07-24"},"268750339":{"id":268750339,"lat":19.1707,"lon":-103.933732,"rt":1,"ciudad":"Pueblo Juárez (La Magdalena)","sug":"Los Regalados","conf":100,"vec":"Mariano Matamoros","celda":"41051","visto":"2026-07-24"},"268750093":{"id":268750093,"lat":19.166709,"lon":-103.933747,"rt":1,"ciudad":"Pueblo Juárez (La Magdalena)","sug":"Hermenegildo Galeana","conf":100,"vec":"","celda":"41051","visto":"2026-07-24"},"268750349":{"id":268750349,"lat":19.171325,"lon":-103.933023,"rt":1,"ciudad":"Pueblo Juárez (La Magdalena)","sug":"Ignacio Zaragoza","conf":100,"vec":"","celda":"41051","visto":"2026-07-24"},"268750095":{"id":268750095,"lat":19.166725,"lon":-103.935026,"rt":1,"ciudad":"Pueblo Juárez (La Magdalena)","sug":"Venustiano Carranza","conf":100,"vec":"","celda":"41051","visto":"2026-07-24"},"268750344":{"id":268750344,"lat":19.17081,"lon":-103.933565,"rt":1,"ciudad":"Pueblo Juárez (La Magdalena)","sug":"Francisco Sarabia","conf":100,"vec":"Constituyentes Eje Poniente","celda":"41051","visto":"2026-07-24"},"268750091":{"id":268750091,"lat":19.167307,"lon":-103.933935,"rt":1,"ciudad":"Pueblo Juárez (La Magdalena)","sug":"Venustiano Carranza","conf":100,"vec":"","celda":"41051","visto":"2026-07-24"},"268884745":{"id":268884745,"lat":19.165435,"lon":-103.929082,"rt":1,"ciudad":"Pueblo Juárez (La Magdalena)","sug":"J. Jesús Alcaraz","conf":100,"vec":"","celda":"41052","visto":"2026-07-24"},"268750100":{"id":268750100,"lat":19.166572,"lon":-103.934927,"rt":1,"ciudad":"Pueblo Juárez (La Magdalena)","sug":"Ignacio Allende","conf":100,"vec":"","celda":"41051","visto":"2026-07-24"},"268750358":{"id":268750358,"lat":19.170342,"lon":-103.93243,"rt":1,"ciudad":"Pueblo Juárez (La Magdalena)","sug":"Ignacio Zaragoza","conf":100,"vec":"","celda":"41051","visto":"2026-07-24"},"268750365":{"id":268750365,"lat":19.16937,"lon":-103.932442,"rt":1,"ciudad":"Pueblo Juárez (La Magdalena)","sug":"Morelos","conf":100,"vec":"","celda":"41051","visto":"2026-07-24"},"268750360":{"id":268750360,"lat":19.169904,"lon":-103.93305,"rt":1,"ciudad":"Pueblo Juárez (La Magdalena)","sug":"Emilio Carranza","conf":100,"vec":"Constituyentes Eje Poniente","celda":"41051","visto":"2026-07-24"},"268750362":{"id":268750362,"lat":19.168797,"lon":-103.93147,"rt":1,"ciudad":"Pueblo Juárez (La Magdalena)","sug":"Ignacio Zaragoza","conf":100,"vec":"","celda":"41051","visto":"2026-07-24"},"268750363":{"id":268750363,"lat":19.170263,"lon":-103.932381,"rt":1,"ciudad":"Pueblo Juárez (La Magdalena)","sug":"Ignacio Zaragoza","conf":100,"vec":"","celda":"41051","visto":"2026-07-24"},"268751392":{"id":268751392,"lat":19.167557,"lon":-103.930708,"rt":1,"ciudad":"Pueblo Juárez (La Magdalena)","sug":"5 de Mayo","conf":100,"vec":"Benito Juárez","celda":"41051","visto":"2026-07-24"},"268751393":{"id":268751393,"lat":19.167991,"lon":-103.930989,"rt":1,"ciudad":"Pueblo Juárez (La Magdalena)","sug":"5 de Mayo","conf":100,"vec":"Hidalgo","celda":"41051","visto":"2026-07-24"},"268751149":{"id":268751149,"lat":19.17032,"lon":-103.932275,"rt":1,"ciudad":"Pueblo Juárez (La Magdalena)","sug":"Emilio Carranza","conf":100,"vec":"","celda":"41051","visto":"2026-07-24"},"268751150":{"id":268751150,"lat":19.171005,"lon":-103.931045,"rt":1,"ciudad":"Pueblo Juárez (La Magdalena)","sug":"Emilio Carranza","conf":100,"vec":"","celda":"41051","visto":"2026-07-24"},"268749878":{"id":268749878,"lat":19.166261,"lon":-103.929869,"rt":1,"ciudad":"Pueblo Juárez (La Magdalena)","sug":"5 de Mayo","conf":100,"vec":"Benito Juárez","celda":"41052","visto":"2026-07-24"},"268885300":{"id":268885300,"lat":19.163945,"lon":-103.930735,"rt":1,"ciudad":"Pueblo Juárez (La Magdalena)","sug":"Emiliano Zapata","conf":100,"vec":"","celda":"41051","visto":"2026-07-24"},"268885299":{"id":268885299,"lat":19.164979,"lon":-103.932095,"rt":1,"ciudad":"Pueblo Juárez (La Magdalena)","sug":"Emiliano Zapata","conf":100,"vec":"Reforma","celda":"41051","visto":"2026-07-24"},"268751421":{"id":268751421,"lat":19.167408,"lon":-103.931,"rt":1,"ciudad":"Pueblo Juárez (La Magdalena)","sug":"Valentín Gómez Farías","conf":100,"vec":"","celda":"41051","visto":"2026-07-24"},"268749886":{"id":268749886,"lat":19.166464,"lon":-103.929142,"rt":1,"ciudad":"Pueblo Juárez (La Magdalena)","sug":"Francisco I. Madero","conf":100,"vec":"Benito Juárez","celda":"41052","visto":"2026-07-24"},"268751422":{"id":268751422,"lat":19.167136,"lon":-103.931538,"rt":1,"ciudad":"Pueblo Juárez (La Magdalena)","sug":"Valentín Gómez Farías","conf":100,"vec":"","celda":"41051","visto":"2026-07-24"},"268751417":{"id":268751417,"lat":19.166453,"lon":-103.931145,"rt":1,"ciudad":"Pueblo Juárez (La Magdalena)","sug":"Valentín Gómez Farías","conf":100,"vec":"Reforma","celda":"41051","visto":"2026-07-24"},"268750415":{"id":268750415,"lat":19.171386,"lon":-103.929422,"rt":1,"ciudad":"Pueblo Juárez (La Magdalena)","sug":"Morelos","conf":100,"vec":"Ing. Adolfo Chávez","celda":"41052","visto":"2026-07-24"},"268750411":{"id":268750411,"lat":19.169919,"lon":-103.928907,"rt":1,"ciudad":"Pueblo Juárez (La Magdalena)","sug":"Profesor Aniceto Castellanos","conf":100,"vec":"","celda":"41052","visto":"2026-07-24"},"268750421":{"id":268750421,"lat":19.170692,"lon":-103.930377,"rt":1,"ciudad":"Pueblo Juárez (La Magdalena)","sug":"Morelos","conf":100,"vec":"","celda":"41051","visto":"2026-07-24"},"268749919":{"id":268749919,"lat":19.164993,"lon":-103.933886,"rt":1,"ciudad":"Pueblo Juárez (La Magdalena)","sug":"Josefa Ortiz de Domínguez","conf":100,"vec":"Reforma","celda":"41051","visto":"2026-07-24"},"268750426":{"id":268750426,"lat":19.169625,"lon":-103.930172,"rt":1,"ciudad":"Pueblo Juárez (La Magdalena)","sug":"20 de Noviembre","conf":100,"vec":"","celda":"41051","visto":"2026-07-24"},"268749924":{"id":268749924,"lat":19.166585,"lon":-103.933677,"rt":1,"ciudad":"Pueblo Juárez (La Magdalena)","sug":"Nicolás Bravo","conf":100,"vec":"Reforma","celda":"41051","visto":"2026-07-24"},"268884068":{"id":268884068,"lat":19.164206,"lon":-103.936418,"rt":1,"ciudad":"Pueblo Juárez (La Magdalena)","sug":"Naranjo","conf":100,"vec":"","celda":"41051","visto":"2026-07-24"},"268749921":{"id":268749921,"lat":19.166351,"lon":-103.934123,"rt":1,"ciudad":"Pueblo Juárez (La Magdalena)","sug":"Independencia","conf":100,"vec":"","celda":"41051","visto":"2026-07-24"},"268750434":{"id":268750434,"lat":19.170181,"lon":-103.931132,"rt":1,"ciudad":"Pueblo Juárez (La Magdalena)","sug":"Morelos","conf":100,"vec":"","celda":"41051","visto":"2026-07-24"},"268750435":{"id":268750435,"lat":19.170064,"lon":-103.931305,"rt":1,"ciudad":"Pueblo Juárez (La Magdalena)","sug":"Morelos","conf":100,"vec":"","celda":"41051","visto":"2026-07-24"},"268884846":{"id":268884846,"lat":19.166415,"lon":-103.927592,"rt":1,"ciudad":"Pueblo Juárez (La Magdalena)","sug":"Gral. Juan José Ríos","conf":100,"vec":"","celda":"41052","visto":"2026-07-24"},"268750445":{"id":268750445,"lat":19.170181,"lon":-103.931132,"rt":1,"ciudad":"Pueblo Juárez (La Magdalena)","sug":"Torres Quintero","conf":100,"vec":"","celda":"41051","visto":"2026-07-24"},"268749678":{"id":268749678,"lat":19.164726,"lon":-103.93371,"rt":1,"ciudad":"Pueblo Juárez (La Magdalena)","sug":"Josefa Ortiz de Domínguez","conf":100,"vec":"Reforma","celda":"41051","visto":"2026-07-24"},"268750190":{"id":268750190,"lat":19.167979,"lon":-103.9339,"rt":1,"ciudad":"Pueblo Juárez (La Magdalena)","sug":"Belisario Domínguez","conf":100,"vec":"","celda":"41051","visto":"2026-07-24"},"268750447":{"id":268750447,"lat":19.169299,"lon":-103.930687,"rt":1,"ciudad":"Pueblo Juárez (La Magdalena)","sug":"Torres Quintero","conf":100,"vec":"","celda":"41051","visto":"2026-07-24"},"268751727":{"id":268751727,"lat":19.17146,"lon":-103.934211,"rt":2,"ciudad":"Pueblo Juárez (La Magdalena)","sug":"Aquiles Serdán","conf":100,"vec":"COL-65 / Augusto Gómez Villanueva (Coalatilla) - Pueblo Juárez (La Magdalena)","celda":"41051","visto":"2026-07-24"},"268749928":{"id":268749928,"lat":19.166845,"lon":-103.93318,"rt":1,"ciudad":"Pueblo Juárez (La Magdalena)","sug":"Independencia","conf":100,"vec":"Mariano Matamoros","celda":"41051","visto":"2026-07-24"},"268749929":{"id":268749929,"lat":19.166585,"lon":-103.933677,"rt":1,"ciudad":"Pueblo Juárez (La Magdalena)","sug":"Independencia","conf":100,"vec":"","celda":"41051","visto":"2026-07-24"},"268750187":{"id":268750187,"lat":19.168279,"lon":-103.934098,"rt":1,"ciudad":"Pueblo Juárez (La Magdalena)","sug":"Vicente Guerrero","conf":100,"vec":"Mariano Matamoros","celda":"41051","visto":"2026-07-24"},"268749942":{"id":268749942,"lat":19.166605,"lon":-103.933015,"rt":1,"ciudad":"Pueblo Juárez (La Magdalena)","sug":"Emiliano Zapata","conf":100,"vec":"Reforma","celda":"41051","visto":"2026-07-24"},"268750460":{"id":268750460,"lat":19.171291,"lon":-103.930533,"rt":1,"ciudad":"Pueblo Juárez (La Magdalena)","sug":"Emilio Carranza","conf":100,"vec":"","celda":"41051","visto":"2026-07-24"},"268750461":{"id":268750461,"lat":19.17222,"lon":-103.929257,"rt":1,"ciudad":"Pueblo Juárez (La Magdalena)","sug":"Emilio Carranza","conf":100,"vec":"Ing. Adolfo Chávez","celda":"41052","visto":"2026-07-24"},"268750463":{"id":268750463,"lat":19.17128,"lon":-103.92992,"rt":1,"ciudad":"Pueblo Juárez (La Magdalena)","sug":"Profesor Aniceto Castellanos","conf":100,"vec":"","celda":"41052","visto":"2026-07-24"},"268751737":{"id":268751737,"lat":19.171201,"lon":-103.934715,"rt":2,"ciudad":"Pueblo Juárez (La Magdalena)","sug":"Revolución","conf":100,"vec":"Mariano Matamoros","celda":"41051","visto":"2026-07-24"},"268750459":{"id":268750459,"lat":19.17047,"lon":-103.930706,"rt":1,"ciudad":"Pueblo Juárez (La Magdalena)","sug":"20 de Noviembre","conf":100,"vec":"","celda":"41051","visto":"2026-07-24"},"268884614":{"id":268884614,"lat":19.166366,"lon":-103.928414,"rt":1,"ciudad":"Pueblo Juárez (La Magdalena)","sug":"J. Jesús Alcaraz","conf":100,"vec":"","celda":"41052","visto":"2026-07-24"},"268884615":{"id":268884615,"lat":19.166801,"lon":-103.92816,"rt":1,"ciudad":"Pueblo Juárez (La Magdalena)","sug":"Gral. Juan José Ríos","conf":100,"vec":"Benito Juárez","celda":"41052","visto":"2026-07-24"},"268750470":{"id":268750470,"lat":19.172652,"lon":-103.930612,"rt":1,"ciudad":"Pueblo Juárez (La Magdalena)","sug":"Francisco Sarabia","conf":100,"vec":"Ing. Adolfo Chávez","celda":"41051","visto":"2026-07-24"},"268884610":{"id":268884610,"lat":19.165404,"lon":-103.92946,"rt":1,"ciudad":"Pueblo Juárez (La Magdalena)","sug":"J. Jesús Alcaraz","conf":100,"vec":"","celda":"41052","visto":"2026-07-24"},"268750466":{"id":268750466,"lat":19.171567,"lon":-103.930127,"rt":1,"ciudad":"Pueblo Juárez (La Magdalena)","sug":"Profesor Aniceto Castellanos","conf":100,"vec":"","celda":"41051","visto":"2026-07-24"},"268750477":{"id":268750477,"lat":19.172015,"lon":-103.93168,"rt":1,"ciudad":"Pueblo Juárez (La Magdalena)","sug":"20 de Noviembre","conf":100,"vec":"","celda":"41051","visto":"2026-07-24"},"268750472":{"id":268750472,"lat":19.171881,"lon":-103.931905,"rt":1,"ciudad":"Pueblo Juárez (La Magdalena)","sug":"Francisco Sarabia","conf":100,"vec":"","celda":"41051","visto":"2026-07-24"},"268884618":{"id":268884618,"lat":19.16768,"lon":-103.927517,"rt":1,"ciudad":"Pueblo Juárez (La Magdalena)","sug":"J. Jesús Alcaraz","conf":100,"vec":"","celda":"41052","visto":"2026-07-24"},"268750473":{"id":268750473,"lat":19.172527,"lon":-103.930821,"rt":1,"ciudad":"Pueblo Juárez (La Magdalena)","sug":"Francisco Sarabia","conf":100,"vec":"","celda":"41051","visto":"2026-07-24"},"268750475":{"id":268750475,"lat":19.171822,"lon":-103.931561,"rt":1,"ciudad":"Pueblo Juárez (La Magdalena)","sug":"20 de Noviembre","conf":100,"vec":"","celda":"41051","visto":"2026-07-24"},"268751252":{"id":268751252,"lat":19.173044,"lon":-103.931182,"rt":1,"ciudad":"Pueblo Juárez (La Magdalena)","sug":"Profesor Aniceto Castellanos","conf":100,"vec":"","celda":"41051","visto":"2026-07-24"},"268749974":{"id":268749974,"lat":19.168207,"lon":-103.930121,"rt":1,"ciudad":"Pueblo Juárez (La Magdalena)","sug":"Francisco I. Madero","conf":100,"vec":"Hidalgo","celda":"41051","visto":"2026-07-24"},"268750231":{"id":268750231,"lat":19.167609,"lon":-103.934297,"rt":1,"ciudad":"Pueblo Juárez (La Magdalena)","sug":"Hermenegildo Galeana","conf":100,"vec":"","celda":"41051","visto":"2026-07-24"},"268750227":{"id":268750227,"lat":19.16825,"lon":-103.934143,"rt":1,"ciudad":"Pueblo Juárez (La Magdalena)","sug":"Vicente Guerrero","conf":100,"vec":"","celda":"41051","visto":"2026-07-24"},"268750483":{"id":268750483,"lat":19.172883,"lon":-103.931078,"rt":1,"ciudad":"Pueblo Juárez (La Magdalena)","sug":"Profesor Aniceto Castellanos","conf":100,"vec":"","celda":"41051","visto":"2026-07-24"},"268750236":{"id":268750236,"lat":19.166725,"lon":-103.935026,"rt":1,"ciudad":"Pueblo Juárez (La Magdalena)","sug":"Ignacio Allende","conf":100,"vec":"","celda":"41051","visto":"2026-07-24"},"268749981":{"id":268749981,"lat":19.168394,"lon":-103.929279,"rt":1,"ciudad":"Pueblo Juárez (La Magdalena)","sug":"Gral. Juan José Ríos","conf":100,"vec":"Hidalgo","celda":"41052","visto":"2026-07-24"},"268750495":{"id":268750495,"lat":19.173769,"lon":-103.929784,"rt":1,"ciudad":"Pueblo Juárez (La Magdalena)","sug":"Aquiles Serdán","conf":100,"vec":"Ing. Adolfo Chávez","celda":"41052","visto":"2026-07-24"},"268750233":{"id":268750233,"lat":19.167414,"lon":-103.935475,"rt":1,"ciudad":"Pueblo Juárez (La Magdalena)","sug":"Vicente Guerrero","conf":100,"vec":"","celda":"41051","visto":"2026-07-24"},"268750489":{"id":268750489,"lat":19.17259,"lon":-103.932035,"rt":2,"ciudad":"Pueblo Juárez (La Magdalena)","sug":"Aquiles Serdán","conf":100,"vec":"","celda":"41051","visto":"2026-07-24"},"268750234":{"id":268750234,"lat":19.166752,"lon":-103.936542,"rt":1,"ciudad":"Pueblo Juárez (La Magdalena)","sug":"Vicente Guerrero","conf":100,"vec":"","celda":"41051","visto":"2026-07-24"},"268750496":{"id":268750496,"lat":19.173156,"lon":-103.930971,"rt":2,"ciudad":"Pueblo Juárez (La Magdalena)","sug":"Aquiles Serdán","conf":100,"vec":"Ing. Adolfo Chávez","celda":"41051","visto":"2026-07-24"},"268750242":{"id":268750242,"lat":19.167971,"lon":-103.935837,"rt":1,"ciudad":"Pueblo Juárez (La Magdalena)","sug":"Ignacio Allende","conf":100,"vec":"","celda":"41051","visto":"2026-07-24"},"268750243":{"id":268750243,"lat":19.168355,"lon":-103.935767,"rt":1,"ciudad":"Pueblo Juárez (La Magdalena)","sug":"Degollado","conf":100,"vec":"","celda":"41051","visto":"2026-07-24"},"268750252":{"id":268750252,"lat":19.168873,"lon":-103.934855,"rt":1,"ciudad":"Pueblo Juárez (La Magdalena)","sug":"Degollado","conf":100,"vec":"","celda":"41051","visto":"2026-07-24"},"268750248":{"id":268750248,"lat":19.168219,"lon":-103.934681,"rt":1,"ciudad":"Pueblo Juárez (La Magdalena)","sug":"Hermenegildo Galeana","conf":100,"vec":"","celda":"41051","visto":"2026-07-24"},"268750005":{"id":268750005,"lat":19.169919,"lon":-103.928907,"rt":1,"ciudad":"Pueblo Juárez (La Magdalena)","sug":"Constitución","conf":100,"vec":"Ing. Adolfo Chávez","celda":"41052","visto":"2026-07-24"},"268883639":{"id":268883639,"lat":19.168151,"lon":-103.936181,"rt":1,"ciudad":"Pueblo Juárez (La Magdalena)","sug":"Degollado","conf":100,"vec":"","celda":"41051","visto":"2026-07-24"},"268750263":{"id":268750263,"lat":19.169829,"lon":-103.933182,"rt":1,"ciudad":"Pueblo Juárez (La Magdalena)","sug":"Degollado","conf":100,"vec":"Mariano Matamoros","celda":"41051","visto":"2026-07-24"},"268750001":{"id":268750001,"lat":19.168964,"lon":-103.928222,"rt":1,"ciudad":"Pueblo Juárez (La Magdalena)","sug":"Manuel Álvarez","conf":100,"vec":"Hidalgo","celda":"41052","visto":"2026-07-24"},"268750257":{"id":268750257,"lat":19.168929,"lon":-103.934525,"rt":1,"ciudad":"Pueblo Juárez (La Magdalena)","sug":"Belisario Domínguez","conf":100,"vec":"","celda":"41051","visto":"2026-07-24"},"268750259":{"id":268750259,"lat":19.169432,"lon":-103.933889,"rt":1,"ciudad":"Pueblo Juárez (La Magdalena)","sug":"Degollado","conf":100,"vec":"Mariano Matamoros","celda":"41051","visto":"2026-07-24"},"268883646":{"id":268883646,"lat":19.165547,"lon":-103.935726,"rt":1,"ciudad":"Pueblo Juárez (La Magdalena)","sug":"Aldama","conf":100,"vec":"","celda":"41051","visto":"2026-07-24"},"268883647":{"id":268883647,"lat":19.16659,"lon":-103.935279,"rt":1,"ciudad":"Pueblo Juárez (La Magdalena)","sug":"Venustiano Carranza","conf":100,"vec":"","celda":"41051","visto":"2026-07-24"},"268883645":{"id":268883645,"lat":19.166163,"lon":-103.936143,"rt":1,"ciudad":"Pueblo Juárez (La Magdalena)","sug":"Aldama","conf":100,"vec":"","celda":"41051","visto":"2026-07-24"},"268883643":{"id":268883643,"lat":19.166752,"lon":-103.936542,"rt":1,"ciudad":"Pueblo Juárez (La Magdalena)","sug":"Aldama","conf":100,"vec":"","celda":"41051","visto":"2026-07-24"},"268883640":{"id":268883640,"lat":19.165547,"lon":-103.935726,"rt":1,"ciudad":"Pueblo Juárez (La Magdalena)","sug":"Independencia","conf":100,"vec":"","celda":"41051","visto":"2026-07-24"},"268750019":{"id":268750019,"lat":19.169701,"lon":-103.928745,"rt":1,"ciudad":"Pueblo Juárez (La Magdalena)","sug":"Profesor Aniceto Castellanos","conf":100,"vec":"Hidalgo","celda":"41052","visto":"2026-07-24"},"268883919":{"id":268883919,"lat":19.165099,"lon":-103.935909,"rt":1,"ciudad":"Pueblo Juárez (La Magdalena)","sug":"Javier Mina","conf":100,"vec":"","celda":"41051","visto":"2026-07-24"},"268750282":{"id":268750282,"lat":19.169885,"lon":-103.93517,"rt":1,"ciudad":"Pueblo Juárez (La Magdalena)","sug":"Belisario Domínguez","conf":100,"vec":"","celda":"41051","visto":"2026-07-24"},"268750283":{"id":268750283,"lat":19.169026,"lon":-103.934591,"rt":1,"ciudad":"Pueblo Juárez (La Magdalena)","sug":"Belisario Domínguez","conf":100,"vec":"","celda":"41051","visto":"2026-07-24"},"268750294":{"id":268750294,"lat":19.169885,"lon":-103.93517,"rt":1,"ciudad":"Pueblo Juárez (La Magdalena)","sug":"Los Regalados","conf":100,"vec":"","celda":"41051","visto":"2026-07-24"},"268883921":{"id":268883921,"lat":19.165099,"lon":-103.936618,"rt":1,"ciudad":"Pueblo Juárez (La Magdalena)","sug":"Independencia","conf":100,"vec":"","celda":"41051","visto":"2026-07-24"},"268750300":{"id":268750300,"lat":19.169124,"lon":-103.936612,"rt":1,"ciudad":"Pueblo Juárez (La Magdalena)","sug":"Ignacio Allende","conf":100,"vec":"","celda":"41051","visto":"2026-07-24"},"268750301":{"id":268750301,"lat":19.168734,"lon":-103.936354,"rt":1,"ciudad":"Pueblo Juárez (La Magdalena)","sug":"Ignacio Allende","conf":100,"vec":"","celda":"41051","visto":"2026-07-24"},"268750047":{"id":268750047,"lat":19.169732,"lon":-103.929263,"rt":1,"ciudad":"Pueblo Juárez (La Magdalena)","sug":"Constitución","conf":100,"vec":"","celda":"41052","visto":"2026-07-24"},"268750296":{"id":268750296,"lat":19.169649,"lon":-103.935627,"rt":1,"ciudad":"Pueblo Juárez (La Magdalena)","sug":"Hermenegildo Galeana","conf":100,"vec":"","celda":"41051","visto":"2026-07-24"},"268750552":{"id":268750552,"lat":19.172289,"lon":-103.932602,"rt":2,"ciudad":"Pueblo Juárez (La Magdalena)","sug":"Aquiles Serdán","conf":100,"vec":"","celda":"41051","visto":"2026-07-24"},"268750041":{"id":268750041,"lat":19.168855,"lon":-103.929635,"rt":1,"ciudad":"Pueblo Juárez (La Magdalena)","sug":"20 de Noviembre","conf":100,"vec":"Hidalgo","celda":"41052","visto":"2026-07-24"},"268750297":{"id":268750297,"lat":19.170417,"lon":-103.936144,"rt":1,"ciudad":"Pueblo Juárez (La Magdalena)","sug":"Hermenegildo Galeana","conf":100,"vec":"","celda":"41051","visto":"2026-07-24"},"268750298":{"id":268750298,"lat":19.169124,"lon":-103.936612,"rt":1,"ciudad":"Pueblo Juárez (La Magdalena)","sug":"Los Regalados","conf":100,"vec":"","celda":"41051","visto":"2026-07-24"},"268750299":{"id":268750299,"lat":19.169381,"lon":-103.936148,"rt":1,"ciudad":"Pueblo Juárez (La Magdalena)","sug":"Los Regalados","conf":100,"vec":"","celda":"41051","visto":"2026-07-24"},"268750051":{"id":268750051,"lat":19.169068,"lon":-103.930567,"rt":1,"ciudad":"Pueblo Juárez (La Magdalena)","sug":"Constitución","conf":100,"vec":"","celda":"41051","visto":"2026-07-24"},"268750062":{"id":268750062,"lat":19.168088,"lon":-103.931052,"rt":1,"ciudad":"Pueblo Juárez (La Magdalena)","sug":"Ignacio Zaragoza","conf":100,"vec":"Hidalgo","celda":"41051","visto":"2026-07-24"},"268750575":{"id":268750575,"lat":19.171068,"lon":-103.934973,"rt":1,"ciudad":"Pueblo Juárez (La Magdalena)","sug":"Revolución","conf":100,"vec":"Mariano Matamoros","celda":"41051","visto":"2026-07-24"},"268750056":{"id":268750056,"lat":19.168393,"lon":-103.930217,"rt":1,"ciudad":"Pueblo Juárez (La Magdalena)","sug":"Torres Quintero","conf":100,"vec":"Hidalgo","celda":"41051","visto":"2026-07-24"},"268750057":{"id":268750057,"lat":19.168984,"lon":-103.930732,"rt":1,"ciudad":"Pueblo Juárez (La Magdalena)","sug":"Constitución","conf":100,"vec":"","celda":"41051","visto":"2026-07-24"},"268662000":{"id":268662000,"lat":19.168853,"lon":-103.933228,"rt":1,"ciudad":"Pueblo Juárez (La Magdalena)","sug":"Vicente Guerrero","conf":100,"vec":"Mariano Matamoros","celda":"41051","visto":"2026-07-24"},"268750579":{"id":268750579,"lat":19.170597,"lon":-103.93581,"rt":1,"ciudad":"Pueblo Juárez (La Magdalena)","sug":"Revolución","conf":100,"vec":"","celda":"41051","visto":"2026-07-24"},"268750078":{"id":268750078,"lat":19.168004,"lon":-103.932695,"rt":1,"ciudad":"Pueblo Juárez (La Magdalena)","sug":"Venustiano Carranza","conf":100,"vec":"Mariano Matamoros","celda":"41051","visto":"2026-07-24"},"268750590":{"id":268750590,"lat":19.16989,"lon":-103.937126,"rt":1,"ciudad":"Pueblo Juárez (La Magdalena)","sug":"Revolución","conf":100,"vec":"","celda":"41051","visto":"2026-07-24"},"268750335":{"id":268750335,"lat":19.170323,"lon":-103.934302,"rt":1,"ciudad":"Pueblo Juárez (La Magdalena)","sug":"Los Regalados","conf":100,"vec":"Mariano Matamoros","celda":"41051","visto":"2026-07-24"},"268750072":{"id":268750072,"lat":19.168251,"lon":-103.9322,"rt":1,"ciudad":"Pueblo Juárez (La Magdalena)","sug":"Constitución","conf":100,"vec":"Constituyentes Eje Poniente","celda":"41051","visto":"2026-07-24"},"268884789":{"id":268884789,"lat":19.165783,"lon":-103.926728,"rt":1,"ciudad":"Pueblo Juárez (La Magdalena)","sug":"Mariana Colosio Riojas","conf":100,"vec":"","celda":"41052","visto":"2026-07-24"},"268885042":{"id":268885042,"lat":19.166303,"lon":-103.925792,"rt":1,"ciudad":"Pueblo Juárez (La Magdalena)","sug":"Diana Laura Riojas de Colosio","conf":100,"vec":"","celda":"41052","visto":"2026-07-24"},"268884794":{"id":268884794,"lat":19.166074,"lon":-103.926204,"rt":1,"ciudad":"Pueblo Juárez (La Magdalena)","sug":"Mariana Colosio Riojas","conf":100,"vec":"","celda":"41052","visto":"2026-07-24"},"268884795":{"id":268884795,"lat":19.166303,"lon":-103.925792,"rt":1,"ciudad":"Pueblo Juárez (La Magdalena)","sug":"Mariana Colosio Riojas","conf":100,"vec":"","celda":"41052","visto":"2026-07-24"},"268884847":{"id":268884847,"lat":19.165817,"lon":-103.926667,"rt":1,"ciudad":"Pueblo Juárez (La Magdalena)","sug":"Gral. Juan José Ríos","conf":100,"vec":"","celda":"41052","visto":"2026-07-24"},"268884850":{"id":268884850,"lat":19.166694,"lon":-103.926599,"rt":1,"ciudad":"Pueblo Juárez (La Magdalena)","sug":"Magdalena de Lino","conf":100,"vec":"","celda":"41052","visto":"2026-07-24"},"268884851":{"id":268884851,"lat":19.166216,"lon":-103.926902,"rt":1,"ciudad":"Pueblo Juárez (La Magdalena)","sug":"Magdalena de Lino","conf":100,"vec":"","celda":"41052","visto":"2026-07-24"},"268884849":{"id":268884849,"lat":19.1664,"lon":-103.926385,"rt":1,"ciudad":"Pueblo Juárez (La Magdalena)","sug":"Manuel Santacruz","conf":100,"vec":"","celda":"41052","visto":"2026-07-24"},"268884619":{"id":268884619,"lat":19.167994,"lon":-103.927559,"rt":1,"ciudad":"Pueblo Juárez (La Magdalena)","sug":"Manuel Álvarez","conf":100,"vec":"Benito Juárez","celda":"41052","visto":"2026-07-24"},"271639867":{"id":271639867,"lat":19.12541,"lon":-103.853845,"rt":2,"ciudad":"Jala","sug":"5 de Mayo","conf":100,"vec":"","celda":"41053","visto":"2026-07-24"},"271639356":{"id":271639356,"lat":19.126505,"lon":-103.856572,"rt":2,"ciudad":"Jala","sug":"Porfirio Tejeda","conf":100,"vec":"COL-97","celda":"41053","visto":"2026-07-24"},"271639359":{"id":271639359,"lat":19.12745,"lon":-103.8554,"rt":1,"ciudad":"Jala","sug":"Francisco I. Madero","conf":100,"vec":"","celda":"41053","visto":"2026-07-24"},"271639297":{"id":271639297,"lat":19.12761,"lon":-103.85406,"rt":1,"ciudad":"Jala","sug":"Felipe Ángeles","conf":100,"vec":"","celda":"41053","visto":"2026-07-24"},"271639299":{"id":271639299,"lat":19.127477,"lon":-103.854127,"rt":1,"ciudad":"Jala","sug":"Emiliano Zapata","conf":100,"vec":"","celda":"41053","visto":"2026-07-24"},"271639300":{"id":271639300,"lat":19.1282,"lon":-103.85376,"rt":1,"ciudad":"Jala","sug":"Emiliano Zapata","conf":100,"vec":"","celda":"41053","visto":"2026-07-24"},"270085981":{"id":270085981,"lat":19.171462,"lon":-103.862124,"rt":1,"ciudad":"La Esperanza","sug":"Sor Juana Inés de la Cruz","conf":100,"vec":"Independencia","celda":"41053","visto":"2026-07-24"},"271639925":{"id":271639925,"lat":19.125861,"lon":-103.854881,"rt":2,"ciudad":"Jala","sug":"Porfirio Tejeda","conf":100,"vec":"","celda":"41053","visto":"2026-07-24"},"271639927":{"id":271639927,"lat":19.126226,"lon":-103.855789,"rt":2,"ciudad":"Jala","sug":"Porfirio Tejeda","conf":100,"vec":"","celda":"41053","visto":"2026-07-24"},"271639929":{"id":271639929,"lat":19.126403,"lon":-103.854628,"rt":1,"ciudad":"Jala","sug":"Emiliano Zapata","conf":100,"vec":"","celda":"41053","visto":"2026-07-24"},"271639393":{"id":271639393,"lat":19.126507,"lon":-103.855769,"rt":1,"ciudad":"Jala","sug":"Lázaro Cárdenas","conf":100,"vec":"","celda":"41053","visto":"2026-07-24"},"271639395":{"id":271639395,"lat":19.125955,"lon":-103.85359,"rt":2,"ciudad":"Jala","sug":"5 de Mayo","conf":100,"vec":"","celda":"41053","visto":"2026-07-24"},"271639397":{"id":271639397,"lat":19.126403,"lon":-103.854628,"rt":1,"ciudad":"Jala","sug":"Francisco Villa","conf":100,"vec":"","celda":"41053","visto":"2026-07-24"},"271639398":{"id":271639398,"lat":19.125955,"lon":-103.85359,"rt":1,"ciudad":"Jala","sug":"Francisco Villa","conf":100,"vec":"","celda":"41053","visto":"2026-07-24"},"271639400":{"id":271639400,"lat":19.127014,"lon":-103.854343,"rt":1,"ciudad":"Jala","sug":"Emiliano Zapata","conf":100,"vec":"","celda":"41053","visto":"2026-07-24"},"271639900":{"id":271639900,"lat":19.124892,"lon":-103.854093,"rt":1,"ciudad":"","sug":"5 de Mayo","conf":100,"vec":"","celda":"41053","visto":"2026-07-24"},"271639901":{"id":271639901,"lat":19.123215,"lon":-103.854806,"rt":1,"ciudad":"","sug":"5 de Mayo","conf":100,"vec":"","celda":"41053","visto":"2026-07-24"},"271639390":{"id":271639390,"lat":19.127247,"lon":-103.855508,"rt":1,"ciudad":"Jala","sug":"Lázaro Cárdenas","conf":100,"vec":"","celda":"41053","visto":"2026-07-24"},"271839670":{"id":271839670,"lat":19.129369,"lon":-103.852703,"rt":1,"ciudad":"","sug":"5 de Mayo","conf":100,"vec":"","celda":"41053","visto":"2026-07-24"},"271639230":{"id":271639230,"lat":19.127894,"lon":-103.852745,"rt":2,"ciudad":"Jala","sug":"5 de Mayo","conf":100,"vec":"","celda":"41053","visto":"2026-07-24"},"271639720":{"id":271639720,"lat":19.127748,"lon":-103.85439,"rt":1,"ciudad":"Jala","sug":"Felipe Ángeles","conf":100,"vec":"","celda":"41053","visto":"2026-07-24"},"271639722":{"id":271639722,"lat":19.127383,"lon":-103.855259,"rt":1,"ciudad":"Jala","sug":"Francisco I. Madero","conf":100,"vec":"","celda":"41053","visto":"2026-07-24"},"271639723":{"id":271639723,"lat":19.127014,"lon":-103.854343,"rt":1,"ciudad":"Jala","sug":"Francisco I. Madero","conf":100,"vec":"","celda":"41053","visto":"2026-07-24"},"271639176":{"id":271639176,"lat":19.128533,"lon":-103.852538,"rt":2,"ciudad":"Jala","sug":"5 de Mayo","conf":100,"vec":"","celda":"41053","visto":"2026-07-24"},"294385230":{"id":294385230,"lat":19.170313,"lon":-103.863637,"rt":1,"ciudad":"La Esperanza","sug":"Sor Juana Inés de la Cruz","conf":100,"vec":"Constitución","celda":"41053","visto":"2026-07-24"},"271639287":{"id":271639287,"lat":19.127183,"lon":-103.853039,"rt":2,"ciudad":"Jala","sug":"5 de Mayo","conf":100,"vec":"","celda":"41053","visto":"2026-07-24"},"271639291":{"id":271639291,"lat":19.126771,"lon":-103.853209,"rt":2,"ciudad":"Jala","sug":"5 de Mayo","conf":100,"vec":"","celda":"41053","visto":"2026-07-24"},"271639294":{"id":271639294,"lat":19.126965,"lon":-103.854224,"rt":1,"ciudad":"Jala","sug":"Francisco I. Madero","conf":100,"vec":"","celda":"41053","visto":"2026-07-24"},"271639232":{"id":271639232,"lat":19.1282,"lon":-103.85376,"rt":1,"ciudad":"Jala","sug":"Benito Juárez","conf":100,"vec":"","celda":"41053","visto":"2026-07-24"},"446726480":{"id":446726480,"lat":19.128047,"lon":-103.855082,"rt":1,"ciudad":"Jala","sug":"Felipe Ángeles","conf":100,"vec":"","celda":"41053","visto":"2026-07-24"},"446726481":{"id":446726481,"lat":19.128057,"lon":-103.855106,"rt":1,"ciudad":"Jala","sug":"Felipe Ángeles","conf":100,"vec":"","celda":"41053","visto":"2026-07-24"},"271639235":{"id":271639235,"lat":19.12858,"lon":-103.853567,"rt":1,"ciudad":"Jala","sug":"Emiliano Zapata","conf":100,"vec":"","celda":"41053","visto":"2026-07-24"},"446726483":{"id":446726483,"lat":19.12745,"lon":-103.8554,"rt":1,"ciudad":"Jala","sug":"Lázaro Cárdenas","conf":100,"vec":"","celda":"41053","visto":"2026-07-24"},"249559221":{"id":249559221,"lat":19.136604,"lon":-103.765036,"rt":1,"ciudad":"Las Golondrinas","sug":"Profesora María Cruz Anguiano","conf":100,"vec":"Camino de Arrieros","celda":"41054","visto":"2026-07-24"},"475669868":{"id":475669868,"lat":19.161587,"lon":-103.701469,"rt":1,"ciudad":"Piscila","sug":"Ignacio Allende","conf":100,"vec":"Francisco I. Madero Nte.","celda":"41055","visto":"2026-07-24"},"271978678":{"id":271978678,"lat":19.174354,"lon":-103.725367,"rt":1,"ciudad":"El Alpuyequito","sug":"Circuito de las Carretas","conf":100,"vec":"","celda":"41055","visto":"2026-07-24"},"271978676":{"id":271978676,"lat":19.173746,"lon":-103.722398,"rt":1,"ciudad":"El Alpuyequito","sug":"Circuito de las Carretas","conf":100,"vec":"","celda":"41055","visto":"2026-07-24"},"271978677":{"id":271978677,"lat":19.173556,"lon":-103.723355,"rt":1,"ciudad":"El Alpuyequito","sug":"Circuito de las Carretas","conf":100,"vec":"","celda":"41055","visto":"2026-07-24"},"333272921":{"id":333272921,"lat":19.162242,"lon":-103.703552,"rt":1,"ciudad":"Piscila","sug":"27 de Septiembre","conf":100,"vec":"27 de Septiembre","celda":"41055","visto":"2026-07-24"},"271978675":{"id":271978675,"lat":19.174843,"lon":-103.722311,"rt":1,"ciudad":"El Alpuyequito","sug":"Circuito de las Carretas","conf":100,"vec":"","celda":"41055","visto":"2026-07-24"},"271978630":{"id":271978630,"lat":19.173746,"lon":-103.722398,"rt":1,"ciudad":"El Alpuyequito","sug":"Circuito de las Carretas","conf":100,"vec":"","celda":"41055","visto":"2026-07-24"}}}