{
 "actualizado": "2026-07-22T02:11:15+00:00",
 "env": "row",
 "total": 41950,
 "estados": [
  {
   "estado": "Campeche",
   "slug": "campeche",
   "total": 57,
   "ciudades": 4
  },
  {
   "estado": "Chiapas",
   "slug": "chiapas",
   "total": 6272,
   "ciudades": 291
  },
  {
   "estado": "Guerrero",
   "slug": "guerrero",
   "total": 8865,
   "ciudades": 224
  },
  {
   "estado": "Michoacán",
   "slug": "michoacan",
   "total": 125,
   "ciudades": 3
  },
  {
   "estado": "Oaxaca",
   "slug": "oaxaca",
   "total": 19497,
   "ciudades": 781
  },
  {
   "estado": "Puebla",
   "slug": "puebla",
   "total": 19,
   "ciudades": 3
  },
  {
   "estado": "Quintana Roo",
   "slug": "quintana-roo",
   "total": 1,
   "ciudades": 1
  },
  {
   "estado": "Sonora",
   "slug": "sonora",
   "total": 2649,
   "ciudades": 57
  },
  {
   "estado": "Tabasco",
   "slug": "tabasco",
   "total": 2148,
   "ciudades": 55
  },
  {
   "estado": "Veracruz",
   "slug": "veracruz",
   "total": 2317,
   "ciudades": 92
  }
 ],
 "progreso": {
  "ciclo": 1,
  "celdas_escaneadas": 31023,
  "celdas_total": 161650,
  "porcentaje": 19.2,
  "modo": "completo"
 },
 "aviso": "",
 "tipos": {
  "1": "Calle",
  "2": "Avenida principal",
  "3": "Autopista",
  "4": "Rampa",
  "5": "Sendero peatonal",
  "6": "Carretera mayor",
  "7": "Carretera menor",
  "8": "Terracería",
  "10": "Andador",
  "15": "Ferry",
  "16": "Escaleras",
  "17": "Camino privado",
  "18": "Vía de tren",
  "19": "Pista de aterrizaje",
  "20": "Camino de estacionamiento",
  "22": "Callejón"
 }
}